{"match_id":"34584f63-8b3a-4285-b2e9-9a7b3f0875db","map_id":"AmbroseValley","date":"February_11","players":{"0d1d4a51-e632-46dd-9686-0e644e73a435":{"is_bot":false,"events":[{"ts":1770810741,"event":"Position","px":726.33,"py":540.88},{"ts":1770810756,"event":"Position","px":721.01,"py":542.53},{"ts":1770810761,"event":"Position","px":689.64,"py":533.13},{"ts":1770810766,"event":"Position","px":673.84,"py":560.28},{"ts":1770810771,"event":"Position","px":667.92,"py":596.26},{"ts":1770810776,"event":"Position","px":659.48,"py":590.43},{"ts":1770810781,"event":"Position","px":640.21,"py":577.36},{"ts":1770810782,"event":"Loot","px":637.91,"py":576.41},{"ts":1770810786,"event":"Position","px":628.05,"py":576.64},{"ts":1770810791,"event":"Position","px":608.49,"py":558.7},{"ts":1770810794,"event":"Loot","px":603.89,"py":556.94},{"ts":1770810797,"event":"Loot","px":605.89,"py":557.23},{"ts":1770810801,"event":"Position","px":606.54,"py":560.57},{"ts":1770810802,"event":"Loot","px":606.54,"py":560.57},{"ts":1770810806,"event":"Position","px":594.91,"py":557.94},{"ts":1770810811,"event":"Position","px":591.69,"py":565.71},{"ts":1770810813,"event":"Loot","px":592.32,"py":569.74},{"ts":1770810814,"event":"Loot","px":591.17,"py":573.25},{"ts":1770810816,"event":"Loot","px":592.28,"py":576.64},{"ts":1770810816,"event":"Position","px":592.28,"py":576.64},{"ts":1770810817,"event":"Loot","px":594.35,"py":576.78},{"ts":1770810821,"event":"Position","px":600.43,"py":567.82},{"ts":1770810826,"event":"Position","px":593.65,"py":567.15},{"ts":1770810831,"event":"Position","px":580.64,"py":579.61},{"ts":1770810835,"event":"Loot","px":583.26,"py":591.25},{"ts":1770810836,"event":"Position","px":587.37,"py":587.75},{"ts":1770810837,"event":"Loot","px":588.97,"py":587.28},{"ts":1770810839,"event":"Loot","px":593.29,"py":590.03},{"ts":1770810841,"event":"Position","px":583.31,"py":585.85},{"ts":1770810846,"event":"Position","px":558.68,"py":594.88},{"ts":1770810851,"event":"Position","px":550.04,"py":585.85},{"ts":1770810856,"event":"Position","px":530.3,"py":579.97},{"ts":1770810857,"event":"BotKill","px":529.76,"py":579.56},{"ts":1770810861,"event":"Position","px":534.88,"py":584.12},{"ts":1770810866,"event":"Position","px":529.9,"py":590.7},{"ts":1770810867,"event":"BotKilled","px":528.71,"py":590.82}]}}}