{"match_id":"70dc76be-d3fb-4498-b732-1d86f552a4e7","map_id":"Lockdown","date":"February_10","players":{"a0738c7c-612e-45c9-b24d-057115642057":{"is_bot":false,"events":[{"ts":1770725303,"event":"Position","px":727.94,"py":290.76},{"ts":1770725323,"event":"Position","px":737.77,"py":298.75},{"ts":1770725328,"event":"Loot","px":754.3,"py":303.58},{"ts":1770725328,"event":"Position","px":754.3,"py":303.58},{"ts":1770725333,"event":"Loot","px":758.96,"py":304.27},{"ts":1770725333,"event":"Position","px":758.96,"py":304.27},{"ts":1770725338,"event":"Position","px":755.41,"py":319.74},{"ts":1770725341,"event":"Loot","px":755.88,"py":319.27},{"ts":1770725343,"event":"Position","px":762.24,"py":325.53},{"ts":1770725348,"event":"Position","px":764.5,"py":331.33},{"ts":1770725353,"event":"Position","px":744.72,"py":329.46},{"ts":1770725355,"event":"Loot","px":744.72,"py":329.46},{"ts":1770725358,"event":"Position","px":730.71,"py":328.55},{"ts":1770725363,"event":"Position","px":703.2,"py":334.42},{"ts":1770725368,"event":"Position","px":684.9,"py":346.89},{"ts":1770725373,"event":"Position","px":667.77,"py":368.56},{"ts":1770725378,"event":"Position","px":651.96,"py":384.59},{"ts":1770725383,"event":"Position","px":638.14,"py":391.99},{"ts":1770725389,"event":"Position","px":621.05,"py":394.26},{"ts":1770725394,"event":"Position","px":615.04,"py":396.6},{"ts":1770725399,"event":"Position","px":596.61,"py":415.05},{"ts":1770725404,"event":"Position","px":588.97,"py":422.44},{"ts":1770725406,"event":"Loot","px":586.2,"py":422.36},{"ts":1770725409,"event":"Position","px":587.17,"py":419.97},{"ts":1770725414,"event":"Position","px":596.24,"py":431.03},{"ts":1770725419,"event":"Position","px":596.97,"py":429.23},{"ts":1770725424,"event":"Position","px":606.97,"py":421.58},{"ts":1770725427,"event":"BotKill","px":604.49,"py":416.55},{"ts":1770725429,"event":"Position","px":601.79,"py":414.67},{"ts":1770725431,"event":"Loot","px":600.7,"py":413.96},{"ts":1770725431,"event":"Loot","px":600.7,"py":413.96},{"ts":1770725444,"event":"Position","px":581.16,"py":409.44},{"ts":1770725449,"event":"Position","px":554.52,"py":417.69},{"ts":1770725454,"event":"Position","px":543.33,"py":434.12},{"ts":1770725459,"event":"Position","px":537.47,"py":447.76},{"ts":1770725463,"event":"BotKill","px":537.63,"py":446.52},{"ts":1770725464,"event":"Position","px":537.63,"py":446.52},{"ts":1770725477,"event":"Loot","px":549.58,"py":443.53},{"ts":1770725479,"event":"Position","px":545.61,"py":441.71},{"ts":1770725484,"event":"Position","px":545.52,"py":438.62},{"ts":1770725489,"event":"Position","px":537.99,"py":450.89},{"ts":1770725489,"event":"Loot","px":537.99,"py":450.89},{"ts":1770725494,"event":"Position","px":530.93,"py":442.9},{"ts":1770725496,"event":"BotKill","px":531.27,"py":443.78},{"ts":1770725499,"event":"Position","px":535.77,"py":442.7},{"ts":1770725504,"event":"Loot","px":549.97,"py":444.68},{"ts":1770725504,"event":"Position","px":549.97,"py":444.68},{"ts":1770725505,"event":"Loot","px":549.97,"py":444.68},{"ts":1770725509,"event":"Position","px":533.47,"py":438.32},{"ts":1770725514,"event":"Position","px":531.8,"py":436.23},{"ts":1770725516,"event":"Loot","px":535.99,"py":433.83},{"ts":1770725519,"event":"Position","px":523.19,"py":441.28},{"ts":1770725524,"event":"Position","px":516.56,"py":440.86},{"ts":1770725525,"event":"Loot","px":516.56,"py":440.86},{"ts":1770725525,"event":"Loot","px":516.56,"py":440.86},{"ts":1770725529,"event":"Position","px":521.32,"py":456.57},{"ts":1770725534,"event":"Position","px":504.96,"py":455.21},{"ts":1770725539,"event":"Position","px":491.71,"py":443.85},{"ts":1770725544,"event":"Position","px":487.46,"py":436.59},{"ts":1770725549,"event":"Position","px":476.6,"py":436.17},{"ts":1770725554,"event":"Position","px":462.39,"py":449.54},{"ts":1770725559,"event":"Position","px":457.91,"py":479.65},{"ts":1770725565,"event":"Position","px":455.14,"py":500.02},{"ts":1770725570,"event":"Position","px":452.09,"py":526.15},{"ts":1770725575,"event":"Position","px":434.89,"py":536.99},{"ts":1770725580,"event":"Position","px":406.8,"py":526.46},{"ts":1770725585,"event":"Position","px":415.27,"py":501.86},{"ts":1770725590,"event":"Position","px":420.16,"py":493.1},{"ts":1770725595,"event":"Position","px":432.66,"py":486.66},{"ts":1770725600,"event":"Position","px":426.23,"py":486.07},{"ts":1770725605,"event":"Position","px":434.24,"py":487.43},{"ts":1770725610,"event":"Position","px":445.87,"py":488.66},{"ts":1770725615,"event":"Position","px":453.56,"py":487.21},{"ts":1770725620,"event":"Position","px":453.77,"py":479.3},{"ts":1770725623,"event":"BotKill","px":446.62,"py":481.97},{"ts":1770725625,"event":"Position","px":446.62,"py":481.97},{"ts":1770725627,"event":"Loot","px":442.51,"py":478.04},{"ts":1770725629,"event":"Loot","px":442.51,"py":478.04},{"ts":1770725630,"event":"Position","px":442.51,"py":478.04},{"ts":1770725630,"event":"Loot","px":442.51,"py":478.04},{"ts":1770725631,"event":"Loot","px":442.51,"py":478.04},{"ts":1770725632,"event":"Loot","px":442.51,"py":478.04},{"ts":1770725634,"event":"Loot","px":442.51,"py":478.04},{"ts":1770725640,"event":"Position","px":442.35,"py":499.69},{"ts":1770725645,"event":"Position","px":438.28,"py":507.88},{"ts":1770725650,"event":"Position","px":439.32,"py":502.26},{"ts":1770725650,"event":"Loot","px":439.11,"py":502.05},{"ts":1770725655,"event":"Position","px":438.79,"py":512.03},{"ts":1770725660,"event":"Position","px":432.51,"py":538.52},{"ts":1770725665,"event":"Position","px":440.75,"py":562.09},{"ts":1770725670,"event":"Position","px":426.12,"py":584.33},{"ts":1770725675,"event":"Position","px":412.91,"py":583.42},{"ts":1770725680,"event":"Position","px":399.75,"py":566.8},{"ts":1770725685,"event":"Position","px":404.45,"py":538.76},{"ts":1770725690,"event":"Position","px":410.21,"py":509.35},{"ts":1770725695,"event":"Position","px":410.09,"py":512.86},{"ts":1770725700,"event":"Position","px":406.74,"py":516.07},{"ts":1770725705,"event":"Position","px":412.62,"py":508.72},{"ts":1770725710,"event":"Position","px":408.49,"py":528.38},{"ts":1770725715,"event":"Position","px":425.9,"py":535.37},{"ts":1770725720,"event":"Position","px":450.1,"py":530.79},{"ts":1770725725,"event":"Position","px":474.66,"py":511.73},{"ts":1770725730,"event":"Position","px":498.91,"py":498.6},{"ts":1770725735,"event":"Position","px":504.83,"py":472.39},{"ts":1770725740,"event":"Position","px":531.14,"py":459.44},{"ts":1770725746,"event":"Position","px":538.48,"py":457.52},{"ts":1770725761,"event":"Position","px":560.21,"py":434.28},{"ts":1770725766,"event":"Position","px":576.44,"py":410.32},{"ts":1770725771,"event":"Position","px":583.06,"py":382.98},{"ts":1770725776,"event":"Position","px":607.04,"py":372.32},{"ts":1770725781,"event":"Position","px":621.12,"py":352.61},{"ts":1770725786,"event":"Position","px":624.09,"py":330.63},{"ts":1770725791,"event":"Position","px":615.18,"py":307.6},{"ts":1770725796,"event":"Position","px":594.53,"py":296.63},{"ts":1770725801,"event":"Position","px":584.36,"py":290.96},{"ts":1770725806,"event":"Position","px":571.26,"py":271.75},{"ts":1770725811,"event":"Position","px":573.62,"py":258.17},{"ts":1770725816,"event":"Position","px":593.53,"py":273.3},{"ts":1770725821,"event":"Loot","px":598.43,"py":267.75},{"ts":1770725821,"event":"Loot","px":598.43,"py":267.75},{"ts":1770725821,"event":"Position","px":598.43,"py":267.75},{"ts":1770725826,"event":"Position","px":612.59,"py":275.79},{"ts":1770725831,"event":"Position","px":610.91,"py":266.36},{"ts":1770725834,"event":"Loot","px":609.98,"py":266.72},{"ts":1770725836,"event":"Position","px":616.45,"py":270.74},{"ts":1770725838,"event":"Loot","px":618.21,"py":278.83},{"ts":1770725841,"event":"Position","px":626.62,"py":275.38},{"ts":1770725846,"event":"Position","px":630.64,"py":278.8},{"ts":1770725856,"event":"Position","px":625.42,"py":276.16},{"ts":1770725861,"event":"Position","px":601.65,"py":284.48},{"ts":1770725871,"event":"Position","px":599.42,"py":280.64},{"ts":1770725876,"event":"Position","px":596.93,"py":274.18},{"ts":1770725881,"event":"Position","px":580.13,"py":269.15},{"ts":1770725886,"event":"Position","px":561.39,"py":267.18},{"ts":1770725896,"event":"Position","px":565.58,"py":264.76},{"ts":1770725937,"event":"Position","px":569.25,"py":267.56},{"ts":1770725942,"event":"Position","px":556.37,"py":272.24},{"ts":1770725952,"event":"Position","px":570.35,"py":265.33},{"ts":1770725957,"event":"Position","px":559.85,"py":259.19},{"ts":1770725962,"event":"Position","px":579.62,"py":238.27},{"ts":1770725967,"event":"Position","px":593.7,"py":213.33},{"ts":1770725972,"event":"Position","px":622.24,"py":203.67},{"ts":1770725975,"event":"Loot","px":629.1,"py":214.16},{"ts":1770725977,"event":"Position","px":632.54,"py":210.01},{"ts":1770725982,"event":"Position","px":642.82,"py":182.79},{"ts":1770725987,"event":"Position","px":646.05,"py":180.62}]}}}