{"match_id":"8bdf85ae-837c-4159-b604-465b0c24e8ab","map_id":"GrandRift","date":"February_13","players":{"ef856044-af5d-40a0-8cf1-b52f933603b9":{"is_bot":false,"events":[{"ts":1770998955,"event":"Position","px":361.57,"py":827.1},{"ts":1770998970,"event":"Position","px":379.03,"py":854.81},{"ts":1770998975,"event":"Position","px":400.86,"py":845.05},{"ts":1770998980,"event":"Position","px":408.89,"py":818.08},{"ts":1770999005,"event":"Position","px":445.42,"py":831.95},{"ts":1770999010,"event":"Position","px":466.78,"py":826.67},{"ts":1770999015,"event":"Position","px":489.26,"py":801.99},{"ts":1770999020,"event":"Position","px":490.66,"py":794.66},{"ts":1770999030,"event":"Position","px":500.81,"py":782.57},{"ts":1770999035,"event":"Position","px":493.5,"py":800.05},{"ts":1770999040,"event":"Position","px":488.28,"py":775.93},{"ts":1770999060,"event":"Position","px":445.04,"py":736.81},{"ts":1770999065,"event":"Position","px":432.16,"py":724.77},{"ts":1770999068,"event":"Loot","px":432.16,"py":724.77},{"ts":1770999068,"event":"Loot","px":432.16,"py":724.77},{"ts":1770999075,"event":"Position","px":440.75,"py":711.76},{"ts":1770999080,"event":"Position","px":482.0,"py":673.77},{"ts":1770999085,"event":"Position","px":527.67,"py":656.34},{"ts":1770999090,"event":"Position","px":526.57,"py":653.14},{"ts":1770999095,"event":"Position","px":525.85,"py":623.75},{"ts":1770999097,"event":"BotKill","px":528.92,"py":613.37},{"ts":1770999098,"event":"BotKilled","px":530.32,"py":610.26},{"ts":1770999100,"event":"Position","px":530.43,"py":610.0}]}}}