{"match_id":"e180cba8-d7db-44c3-b59b-2bdd9304f136","map_id":"AmbroseValley","date":"February_13","players":{"9a160956-c2be-4a8c-aa1a-c98fe7cc5792":{"is_bot":false,"events":[{"ts":1770965454,"event":"Position","px":104.74,"py":896.49},{"ts":1770965469,"event":"Position","px":109.63,"py":896.13},{"ts":1770965474,"event":"Position","px":114.47,"py":894.88},{"ts":1770965484,"event":"Position","px":133.3,"py":885.82},{"ts":1770965489,"event":"Position","px":159.04,"py":875.47},{"ts":1770965494,"event":"Position","px":169.04,"py":882.44},{"ts":1770965499,"event":"Position","px":171.36,"py":880.36},{"ts":1770965500,"event":"Loot","px":173.79,"py":876.53},{"ts":1770965504,"event":"Position","px":178.08,"py":871.72},{"ts":1770965510,"event":"BotKill","px":176.47,"py":871.09},{"ts":1770965514,"event":"Position","px":178.94,"py":873.99},{"ts":1770965518,"event":"Loot","px":195.55,"py":862.19},{"ts":1770965519,"event":"Loot","px":195.55,"py":862.19},{"ts":1770965519,"event":"Position","px":195.55,"py":862.19},{"ts":1770965524,"event":"Position","px":192.01,"py":857.21},{"ts":1770965527,"event":"Loot","px":203.38,"py":848.21},{"ts":1770965529,"event":"Position","px":206.03,"py":850.13},{"ts":1770965534,"event":"Position","px":217.44,"py":853.33},{"ts":1770965539,"event":"Position","px":199.72,"py":862.38},{"ts":1770965544,"event":"Position","px":186.51,"py":864.98},{"ts":1770965549,"event":"Position","px":178.08,"py":847.48},{"ts":1770965551,"event":"Loot","px":180.93,"py":840.25},{"ts":1770965554,"event":"Position","px":177.26,"py":842.76},{"ts":1770965559,"event":"Position","px":177.36,"py":850.18},{"ts":1770965564,"event":"Position","px":171.02,"py":855.72},{"ts":1770965569,"event":"Loot","px":167.86,"py":851.65},{"ts":1770965569,"event":"Position","px":167.86,"py":851.65},{"ts":1770965574,"event":"Position","px":162.33,"py":870.58},{"ts":1770965577,"event":"Loot","px":161.99,"py":871.07},{"ts":1770965584,"event":"Position","px":166.94,"py":863.67},{"ts":1770965589,"event":"Position","px":176.81,"py":849.49},{"ts":1770965594,"event":"Position","px":171.67,"py":861.68},{"ts":1770965595,"event":"Loot","px":171.67,"py":861.68},{"ts":1770965604,"event":"Position","px":178.21,"py":867.62},{"ts":1770965609,"event":"Position","px":195.18,"py":866.04},{"ts":1770965615,"event":"Position","px":210.88,"py":856.64},{"ts":1770965620,"event":"Position","px":214.94,"py":861.66},{"ts":1770965625,"event":"Position","px":225.01,"py":868.38},{"ts":1770965627,"event":"Loot","px":225.53,"py":873.36},{"ts":1770965635,"event":"Position","px":217.57,"py":854.18},{"ts":1770965640,"event":"Position","px":207.83,"py":856.15},{"ts":1770965650,"event":"Position","px":224.03,"py":871.44},{"ts":1770965655,"event":"Position","px":232.12,"py":871.05},{"ts":1770965660,"event":"Position","px":237.05,"py":869.65},{"ts":1770965665,"event":"Position","px":245.89,"py":858.85},{"ts":1770965670,"event":"Position","px":258.07,"py":842.38},{"ts":1770965675,"event":"Position","px":273.71,"py":821.22},{"ts":1770965680,"event":"Position","px":276.63,"py":813.18},{"ts":1770965685,"event":"Position","px":282.88,"py":789.87},{"ts":1770965690,"event":"Position","px":286.02,"py":773.84},{"ts":1770965695,"event":"Position","px":294.26,"py":778.74},{"ts":1770965700,"event":"Position","px":306.56,"py":785.4},{"ts":1770965700,"event":"Loot","px":306.56,"py":785.4},{"ts":1770965705,"event":"Position","px":300.85,"py":794.15},{"ts":1770965710,"event":"Position","px":308.38,"py":821.88},{"ts":1770965715,"event":"Position","px":326.3,"py":808.3},{"ts":1770965720,"event":"Position","px":356.2,"py":797.11},{"ts":1770965725,"event":"Position","px":368.33,"py":820.37},{"ts":1770965730,"event":"Position","px":380.83,"py":847.49},{"ts":1770965735,"event":"Position","px":378.0,"py":866.67},{"ts":1770965740,"event":"Position","px":361.36,"py":875.16},{"ts":1770965745,"event":"Position","px":356.68,"py":879.66},{"ts":1770965747,"event":"Loot","px":354.83,"py":883.04},{"ts":1770965755,"event":"Loot","px":357.51,"py":880.83},{"ts":1770965759,"event":"Loot","px":359.1,"py":889.56},{"ts":1770965760,"event":"Position","px":360.28,"py":888.48},{"ts":1770965765,"event":"Position","px":366.3,"py":884.11},{"ts":1770965770,"event":"Position","px":374.46,"py":894.06},{"ts":1770965771,"event":"Loot","px":374.46,"py":894.06},{"ts":1770965772,"event":"Loot","px":374.37,"py":894.58},{"ts":1770965774,"event":"Loot","px":373.52,"py":894.67},{"ts":1770965784,"event":"Loot","px":372.41,"py":888.97},{"ts":1770965790,"event":"Position","px":374.41,"py":880.56},{"ts":1770965796,"event":"Position","px":349.36,"py":870.94},{"ts":1770965801,"event":"Position","px":320.39,"py":848.71},{"ts":1770965806,"event":"Position","px":308.98,"py":820.53},{"ts":1770965811,"event":"Position","px":299.64,"py":795.95},{"ts":1770965816,"event":"Position","px":285.69,"py":767.78},{"ts":1770965821,"event":"Position","px":266.71,"py":744.53},{"ts":1770965826,"event":"Position","px":261.89,"py":724.88},{"ts":1770965831,"event":"Position","px":260.36,"py":694.88},{"ts":1770965836,"event":"Position","px":263.2,"py":666.16},{"ts":1770965841,"event":"Position","px":269.36,"py":629.66},{"ts":1770965846,"event":"Position","px":266.59,"py":603.26},{"ts":1770965851,"event":"Position","px":263.81,"py":586.73},{"ts":1770965856,"event":"Position","px":265.33,"py":569.88},{"ts":1770965861,"event":"Position","px":262.37,"py":564.92},{"ts":1770965866,"event":"Position","px":256.11,"py":553.21},{"ts":1770965871,"event":"Position","px":242.53,"py":555.83},{"ts":1770965876,"event":"Position","px":229.2,"py":535.55},{"ts":1770965881,"event":"Position","px":235.48,"py":520.35},{"ts":1770965886,"event":"Position","px":255.04,"py":523.75},{"ts":1770965891,"event":"Position","px":266.21,"py":533.62},{"ts":1770965896,"event":"Position","px":264.32,"py":549.09},{"ts":1770965901,"event":"Position","px":270.9,"py":537.63},{"ts":1770965906,"event":"Position","px":273.52,"py":523.83},{"ts":1770965911,"event":"Position","px":261.21,"py":514.28},{"ts":1770965911,"event":"Loot","px":261.21,"py":514.28},{"ts":1770965912,"event":"Loot","px":261.21,"py":514.28},{"ts":1770965913,"event":"Loot","px":261.21,"py":514.28},{"ts":1770965916,"event":"Position","px":270.16,"py":515.26},{"ts":1770965921,"event":"Position","px":271.55,"py":529.65},{"ts":1770965926,"event":"Position","px":262.42,"py":550.44},{"ts":1770965931,"event":"Position","px":248.82,"py":551.97},{"ts":1770965936,"event":"Position","px":235.16,"py":539.01},{"ts":1770965941,"event":"Position","px":232.57,"py":520.26},{"ts":1770965946,"event":"Position","px":249.35,"py":511.89},{"ts":1770965951,"event":"Position","px":264.13,"py":513.28},{"ts":1770965956,"event":"Position","px":268.34,"py":515.69},{"ts":1770965961,"event":"Position","px":259.64,"py":512.87},{"ts":1770965971,"event":"Position","px":255.82,"py":511.21},{"ts":1770965977,"event":"Position","px":232.26,"py":509.61},{"ts":1770965982,"event":"Position","px":223.96,"py":521.57},{"ts":1770965987,"event":"Position","px":229.34,"py":531.78},{"ts":1770965992,"event":"Position","px":241.57,"py":549.08},{"ts":1770965997,"event":"Position","px":245.08,"py":558.91},{"ts":1770966002,"event":"Position","px":254.77,"py":552.43},{"ts":1770966002,"event":"BotKilled","px":254.74,"py":552.44}]}}}