{"match_id":"ed07a212-8b5b-47ec-b110-3bfbec14d5b6","map_id":"Lockdown","date":"February_11","players":{"1405":{"is_bot":true,"events":[{"ts":1770834349,"event":"BotPosition","px":168.16,"py":628.68},{"ts":1770834354,"event":"BotPosition","px":167.22,"py":631.08},{"ts":1770834359,"event":"BotPosition","px":152.82,"py":625.5},{"ts":1770834364,"event":"BotPosition","px":147.53,"py":635.69},{"ts":1770834370,"event":"BotPosition","px":158.72,"py":625.46},{"ts":1770834375,"event":"BotPosition","px":175.39,"py":612.71},{"ts":1770834380,"event":"BotPosition","px":192.97,"py":616.14},{"ts":1770834385,"event":"BotPosition","px":187.08,"py":616.17},{"ts":1770834390,"event":"BotPosition","px":194.91,"py":610.53},{"ts":1770834395,"event":"BotPosition","px":188.18,"py":614.49},{"ts":1770834400,"event":"BotPosition","px":192.03,"py":613.82},{"ts":1770834405,"event":"BotPosition","px":214.27,"py":609.79},{"ts":1770834410,"event":"BotPosition","px":218.58,"py":620.27},{"ts":1770834415,"event":"BotPosition","px":216.59,"py":600.92},{"ts":1770834420,"event":"BotPosition","px":222.25,"py":608.84},{"ts":1770834425,"event":"BotPosition","px":211.34,"py":611.27},{"ts":1770834430,"event":"BotPosition","px":209.11,"py":595.11},{"ts":1770834435,"event":"BotPosition","px":205.0,"py":586.97},{"ts":1770834440,"event":"BotPosition","px":214.52,"py":592.68},{"ts":1770834445,"event":"BotPosition","px":217.89,"py":587.06},{"ts":1770834450,"event":"BotPosition","px":236.47,"py":580.51},{"ts":1770834455,"event":"BotPosition","px":250.11,"py":579.9},{"ts":1770834460,"event":"BotPosition","px":270.63,"py":577.99},{"ts":1770834465,"event":"BotPosition","px":293.71,"py":576.01},{"ts":1770834470,"event":"BotPosition","px":302.99,"py":564.17},{"ts":1770834475,"event":"BotPosition","px":314.31,"py":549.75},{"ts":1770834480,"event":"BotPosition","px":333.1,"py":541.98},{"ts":1770834490,"event":"BotPosition","px":334.01,"py":545.84},{"ts":1770834495,"event":"BotPosition","px":315.97,"py":558.27},{"ts":1770834500,"event":"BotPosition","px":331.1,"py":546.8},{"ts":1770834505,"event":"BotPosition","px":350.08,"py":561.34},{"ts":1770834510,"event":"BotPosition","px":353.37,"py":576.07},{"ts":1770834515,"event":"BotPosition","px":345.95,"py":596.84},{"ts":1770834520,"event":"BotPosition","px":333.79,"py":595.88},{"ts":1770834525,"event":"BotPosition","px":324.72,"py":599.58},{"ts":1770834530,"event":"BotPosition","px":336.94,"py":602.9},{"ts":1770834535,"event":"BotPosition","px":359.23,"py":613.3},{"ts":1770834540,"event":"BotPosition","px":376.37,"py":627.22},{"ts":1770834546,"event":"BotPosition","px":377.27,"py":619.58},{"ts":1770834551,"event":"BotPosition","px":384.45,"py":599.63},{"ts":1770834556,"event":"BotPosition","px":374.82,"py":607.82},{"ts":1770834561,"event":"BotPosition","px":357.22,"py":615.78},{"ts":1770834566,"event":"BotPosition","px":333.53,"py":610.11},{"ts":1770834571,"event":"BotPosition","px":344.02,"py":615.18},{"ts":1770834576,"event":"BotPosition","px":364.95,"py":611.07},{"ts":1770834580,"event":"BotKill","px":370.72,"py":608.36},{"ts":1770834581,"event":"BotPosition","px":375.17,"py":608.44},{"ts":1770834586,"event":"BotPosition","px":394.32,"py":601.35},{"ts":1770834591,"event":"BotPosition","px":382.64,"py":598.39},{"ts":1770834596,"event":"BotPosition","px":364.63,"py":599.93},{"ts":1770834601,"event":"BotPosition","px":343.53,"py":595.23},{"ts":1770834611,"event":"BotPosition","px":372.31,"py":598.01},{"ts":1770834616,"event":"BotPosition","px":385.47,"py":597.31},{"ts":1770834621,"event":"BotPosition","px":360.49,"py":599.73},{"ts":1770834626,"event":"BotPosition","px":340.07,"py":597.29},{"ts":1770834631,"event":"BotPosition","px":341.09,"py":574.8},{"ts":1770834636,"event":"BotPosition","px":329.78,"py":570.61},{"ts":1770834646,"event":"BotPosition","px":336.36,"py":569.83},{"ts":1770834651,"event":"BotPosition","px":358.03,"py":565.42},{"ts":1770834656,"event":"BotPosition","px":371.64,"py":559.23},{"ts":1770834661,"event":"BotPosition","px":390.14,"py":559.23},{"ts":1770834666,"event":"BotPosition","px":409.62,"py":544.23},{"ts":1770834671,"event":"BotPosition","px":425.96,"py":525.35},{"ts":1770834676,"event":"BotPosition","px":440.03,"py":506.63},{"ts":1770834681,"event":"BotPosition","px":444.81,"py":498.96},{"ts":1770834682,"event":"BotKill","px":444.87,"py":498.66},{"ts":1770834691,"event":"BotPosition","px":455.0,"py":502.32},{"ts":1770834696,"event":"BotPosition","px":479.61,"py":505.17},{"ts":1770834701,"event":"BotPosition","px":504.43,"py":507.21},{"ts":1770834706,"event":"BotPosition","px":528.09,"py":504.38},{"ts":1770834711,"event":"BotPosition","px":541.55,"py":508.68},{"ts":1770834716,"event":"BotPosition","px":559.51,"py":524.45},{"ts":1770834722,"event":"BotPosition","px":582.57,"py":524.46},{"ts":1770834727,"event":"BotPosition","px":607.11,"py":519.18},{"ts":1770834732,"event":"BotPosition","px":625.83,"py":515.48},{"ts":1770834737,"event":"BotPosition","px":646.22,"py":511.7},{"ts":1770834742,"event":"BotPosition","px":639.03,"py":512.13},{"ts":1770834747,"event":"BotPosition","px":621.75,"py":514.12},{"ts":1770834752,"event":"BotPosition","px":617.26,"py":508.17},{"ts":1770834757,"event":"BotPosition","px":626.19,"py":503.66},{"ts":1770834762,"event":"BotPosition","px":626.48,"py":501.16},{"ts":1770834767,"event":"BotPosition","px":624.58,"py":500.26},{"ts":1770834772,"event":"BotPosition","px":625.14,"py":496.58},{"ts":1770834777,"event":"BotPosition","px":629.68,"py":506.77},{"ts":1770834782,"event":"BotPosition","px":630.04,"py":525.02},{"ts":1770834787,"event":"BotPosition","px":628.89,"py":508.08},{"ts":1770834792,"event":"BotPosition","px":607.43,"py":511.66},{"ts":1770834797,"event":"BotPosition","px":603.71,"py":532.85},{"ts":1770834802,"event":"BotPosition","px":609.31,"py":544.11},{"ts":1770834807,"event":"BotPosition","px":614.93,"py":547.8},{"ts":1770834812,"event":"BotPosition","px":611.64,"py":552.39},{"ts":1770834817,"event":"BotPosition","px":622.07,"py":546.83},{"ts":1770834822,"event":"BotPosition","px":628.31,"py":536.07},{"ts":1770834827,"event":"BotPosition","px":621.73,"py":530.1},{"ts":1770834832,"event":"BotPosition","px":641.11,"py":521.67},{"ts":1770834837,"event":"BotPosition","px":656.31,"py":509.73},{"ts":1770834842,"event":"BotPosition","px":642.2,"py":511.85},{"ts":1770834847,"event":"BotPosition","px":638.5,"py":502.9},{"ts":1770834852,"event":"BotPosition","px":620.96,"py":490.53},{"ts":1770834855,"event":"BotKilled","px":618.29,"py":479.35}]},"1408":{"is_bot":true,"events":[{"ts":1770834349,"event":"BotPosition","px":166.66,"py":626.86},{"ts":1770834354,"event":"BotPosition","px":177.63,"py":625.9},{"ts":1770834359,"event":"BotPosition","px":198.45,"py":612.05},{"ts":1770834364,"event":"BotPosition","px":199.49,"py":621.18},{"ts":1770834370,"event":"BotPosition","px":199.87,"py":617.45},{"ts":1770834375,"event":"BotPosition","px":211.98,"py":617.43},{"ts":1770834380,"event":"BotPosition","px":219.19,"py":625.24},{"ts":1770834385,"event":"BotPosition","px":218.43,"py":622.52},{"ts":1770834395,"event":"BotPosition","px":214.73,"py":615.42},{"ts":1770834400,"event":"BotPosition","px":213.5,"py":609.67},{"ts":1770834405,"event":"BotPosition","px":199.85,"py":621.68},{"ts":1770834410,"event":"BotPosition","px":212.86,"py":620.72},{"ts":1770834415,"event":"BotPosition","px":231.98,"py":633.59},{"ts":1770834420,"event":"BotPosition","px":230.2,"py":623.32},{"ts":1770834425,"event":"BotPosition","px":231.31,"py":624.91},{"ts":1770834430,"event":"BotPosition","px":218.01,"py":606.41},{"ts":1770834435,"event":"BotPosition","px":217.76,"py":587.24},{"ts":1770834440,"event":"BotPosition","px":216.65,"py":599.54},{"ts":1770834445,"event":"BotPosition","px":223.27,"py":584.27},{"ts":1770834450,"event":"BotPosition","px":226.44,"py":592.09},{"ts":1770834455,"event":"BotPosition","px":239.57,"py":593.12},{"ts":1770834460,"event":"BotPosition","px":256.8,"py":590.44},{"ts":1770834465,"event":"BotPosition","px":270.62,"py":600.69},{"ts":1770834470,"event":"BotPosition","px":281.0,"py":593.82},{"ts":1770834475,"event":"BotPosition","px":296.42,"py":580.99},{"ts":1770834480,"event":"BotPosition","px":304.43,"py":562.52},{"ts":1770834485,"event":"BotPosition","px":324.91,"py":549.87},{"ts":1770834490,"event":"BotPosition","px":335.51,"py":553.76},{"ts":1770834495,"event":"BotPosition","px":339.28,"py":555.99},{"ts":1770834500,"event":"BotPosition","px":343.03,"py":558.2},{"ts":1770834505,"event":"BotPosition","px":346.68,"py":560.37},{"ts":1770834510,"event":"BotPosition","px":350.33,"py":562.53},{"ts":1770834515,"event":"BotPosition","px":353.98,"py":564.69},{"ts":1770834525,"event":"BotPosition","px":355.07,"py":571.7},{"ts":1770834530,"event":"BotPosition","px":354.26,"py":575.83},{"ts":1770834534,"event":"BotKilled","px":353.64,"py":578.97}]},"1418":{"is_bot":true,"events":[{"ts":1770834354,"event":"BotPosition","px":714.27,"py":305.05},{"ts":1770834359,"event":"BotPosition","px":704.2,"py":318.09},{"ts":1770834370,"event":"BotPosition","px":696.43,"py":330.62},{"ts":1770834375,"event":"BotPosition","px":692.94,"py":346.11},{"ts":1770834380,"event":"BotPosition","px":681.66,"py":358.06},{"ts":1770834385,"event":"BotPosition","px":664.4,"py":376.46},{"ts":1770834390,"event":"BotPosition","px":657.67,"py":399.93},{"ts":1770834395,"event":"BotPosition","px":651.65,"py":424.14},{"ts":1770834400,"event":"BotPosition","px":628.21,"py":426.92},{"ts":1770834405,"event":"BotPosition","px":614.24,"py":435.6},{"ts":1770834410,"event":"BotPosition","px":615.81,"py":450.06},{"ts":1770834415,"event":"BotPosition","px":623.85,"py":469.14},{"ts":1770834420,"event":"BotPosition","px":623.87,"py":480.6},{"ts":1770834425,"event":"BotPosition","px":624.63,"py":494.71},{"ts":1770834430,"event":"BotPosition","px":612.0,"py":515.1},{"ts":1770834435,"event":"BotPosition","px":594.97,"py":533.76},{"ts":1770834440,"event":"BotPosition","px":577.94,"py":552.4},{"ts":1770834445,"event":"BotPosition","px":575.46,"py":567.37},{"ts":1770834450,"event":"BotPosition","px":556.3,"py":576.72},{"ts":1770834455,"event":"BotPosition","px":532.58,"py":585.11},{"ts":1770834460,"event":"BotPosition","px":515.0,"py":602.28},{"ts":1770834465,"event":"BotPosition","px":499.93,"py":621.41},{"ts":1770834480,"event":"BotPosition","px":488.19,"py":631.51},{"ts":1770834485,"event":"BotPosition","px":480.97,"py":638.23},{"ts":1770834490,"event":"BotPosition","px":475.57,"py":646.5},{"ts":1770834495,"event":"BotPosition","px":477.2,"py":645.8},{"ts":1770834500,"event":"BotPosition","px":478.93,"py":642.88},{"ts":1770834505,"event":"BotPosition","px":478.53,"py":638.86},{"ts":1770834515,"event":"BotPosition","px":484.33,"py":634.09},{"ts":1770834520,"event":"BotPosition","px":487.41,"py":631.29},{"ts":1770834525,"event":"BotPosition","px":490.54,"py":629.44},{"ts":1770834530,"event":"BotPosition","px":488.86,"py":630.53},{"ts":1770834540,"event":"BotKilled","px":489.3,"py":630.85}]},"1422":{"is_bot":true,"events":[{"ts":1770834354,"event":"BotPosition","px":739.12,"py":294.83},{"ts":1770834359,"event":"BotPosition","px":716.4,"py":304.28},{"ts":1770834364,"event":"BotPosition","px":701.73,"py":304.8},{"ts":1770834370,"event":"BotPosition","px":707.43,"py":317.94},{"ts":1770834375,"event":"BotPosition","px":697.38,"py":326.93},{"ts":1770834380,"event":"BotPosition","px":697.26,"py":334.49},{"ts":1770834385,"event":"BotPosition","px":684.06,"py":351.08},{"ts":1770834390,"event":"BotPosition","px":669.0,"py":362.16},{"ts":1770834395,"event":"BotPosition","px":662.57,"py":382.09},{"ts":1770834400,"event":"BotPosition","px":658.91,"py":395.67},{"ts":1770834405,"event":"BotPosition","px":654.12,"py":414.53},{"ts":1770834410,"event":"BotPosition","px":638.96,"py":422.96},{"ts":1770834415,"event":"BotPosition","px":628.66,"py":418.64},{"ts":1770834420,"event":"BotPosition","px":618.32,"py":434.82},{"ts":1770834425,"event":"BotPosition","px":612.35,"py":449.45},{"ts":1770834430,"event":"BotPosition","px":628.82,"py":463.19},{"ts":1770834435,"event":"BotPosition","px":625.03,"py":480.77},{"ts":1770834440,"event":"BotPosition","px":629.5,"py":500.45},{"ts":1770834445,"event":"BotPosition","px":632.45,"py":517.54},{"ts":1770834450,"event":"BotPosition","px":632.05,"py":513.83},{"ts":1770834455,"event":"BotPosition","px":630.38,"py":519.48},{"ts":1770834460,"event":"BotPosition","px":618.95,"py":534.41},{"ts":1770834470,"event":"BotPosition","px":632.41,"py":532.76},{"ts":1770834475,"event":"BotPosition","px":628.35,"py":532.27},{"ts":1770834480,"event":"BotPosition","px":632.59,"py":532.92},{"ts":1770834490,"event":"BotPosition","px":632.58,"py":531.79},{"ts":1770834505,"event":"BotPosition","px":629.23,"py":532.56},{"ts":1770834510,"event":"BotPosition","px":630.63,"py":531.95},{"ts":1770834515,"event":"BotPosition","px":629.48,"py":532.45},{"ts":1770834520,"event":"BotPosition","px":632.39,"py":531.51},{"ts":1770834527,"event":"BotKilled","px":632.49,"py":531.5}]},"1425":{"is_bot":true,"events":[{"ts":1770834354,"event":"BotPosition","px":722.17,"py":309.83},{"ts":1770834359,"event":"BotPosition","px":702.79,"py":324.29},{"ts":1770834364,"event":"BotPosition","px":687.47,"py":343.06},{"ts":1770834370,"event":"BotPosition","px":697.2,"py":332.26},{"ts":1770834375,"event":"BotPosition","px":714.89,"py":326.43},{"ts":1770834380,"event":"BotPosition","px":695.33,"py":333.49},{"ts":1770834385,"event":"BotPosition","px":682.65,"py":349.14},{"ts":1770834390,"event":"BotPosition","px":670.07,"py":359.22},{"ts":1770834395,"event":"BotPosition","px":664.68,"py":375.8},{"ts":1770834400,"event":"BotPosition","px":657.91,"py":396.54},{"ts":1770834405,"event":"BotPosition","px":658.85,"py":421.64},{"ts":1770834410,"event":"BotPosition","px":657.01,"py":427.06},{"ts":1770834415,"event":"BotPosition","px":645.0,"py":405.57},{"ts":1770834420,"event":"BotPosition","px":647.9,"py":408.43},{"ts":1770834425,"event":"BotPosition","px":645.89,"py":427.45},{"ts":1770834430,"event":"BotPosition","px":626.71,"py":432.0},{"ts":1770834435,"event":"BotPosition","px":606.72,"py":446.55},{"ts":1770834440,"event":"BotPosition","px":621.43,"py":459.62},{"ts":1770834445,"event":"BotPosition","px":623.91,"py":481.61},{"ts":1770834450,"event":"BotPosition","px":620.23,"py":504.69},{"ts":1770834455,"event":"BotPosition","px":600.09,"py":519.93},{"ts":1770834460,"event":"BotPosition","px":589.48,"py":539.07},{"ts":1770834465,"event":"BotPosition","px":576.23,"py":559.52},{"ts":1770834470,"event":"BotPosition","px":562.28,"py":571.66},{"ts":1770834475,"event":"BotPosition","px":548.58,"py":574.46},{"ts":1770834480,"event":"BotPosition","px":526.99,"py":587.45},{"ts":1770834485,"event":"BotPosition","px":527.39,"py":601.57},{"ts":1770834490,"event":"BotPosition","px":505.51,"py":613.28},{"ts":1770834495,"event":"BotPosition","px":501.28,"py":603.43},{"ts":1770834500,"event":"BotPosition","px":498.87,"py":618.68},{"ts":1770834505,"event":"BotPosition","px":495.82,"py":623.81},{"ts":1770834510,"event":"BotPosition","px":500.77,"py":623.98},{"ts":1770834515,"event":"BotPosition","px":507.48,"py":617.46},{"ts":1770834520,"event":"BotPosition","px":500.55,"py":619.21},{"ts":1770834525,"event":"BotPosition","px":490.02,"py":630.93},{"ts":1770834540,"event":"BotKilled","px":489.3,"py":629.23}]},"1428":{"is_bot":true,"events":[{"ts":1770834354,"event":"BotPosition","px":176.37,"py":389.13},{"ts":1770834359,"event":"BotPosition","px":187.71,"py":400.05},{"ts":1770834364,"event":"BotPosition","px":199.88,"py":407.45},{"ts":1770834370,"event":"BotPosition","px":208.88,"py":417.7},{"ts":1770834375,"event":"BotPosition","px":216.55,"py":425.36},{"ts":1770834380,"event":"BotPosition","px":220.82,"py":437.45},{"ts":1770834385,"event":"BotPosition","px":230.2,"py":449.59},{"ts":1770834390,"event":"BotPosition","px":225.76,"py":459.28},{"ts":1770834395,"event":"BotPosition","px":226.51,"py":466.78},{"ts":1770834400,"event":"BotPosition","px":227.52,"py":490.85},{"ts":1770834405,"event":"BotPosition","px":233.37,"py":514.79},{"ts":1770834410,"event":"BotPosition","px":242.69,"py":537.71},{"ts":1770834415,"event":"BotPosition","px":262.75,"py":552.14},{"ts":1770834420,"event":"BotPosition","px":285.22,"py":556.59},{"ts":1770834425,"event":"BotPosition","px":306.57,"py":545.07},{"ts":1770834430,"event":"BotPosition","px":310.99,"py":520.59},{"ts":1770834435,"event":"BotPosition","px":308.9,"py":505.28},{"ts":1770834440,"event":"BotPosition","px":313.23,"py":525.81},{"ts":1770834445,"event":"BotPosition","px":323.81,"py":546.55},{"ts":1770834450,"event":"BotPosition","px":345.46,"py":559.56},{"ts":1770834455,"event":"BotPosition","px":360.04,"py":577.13},{"ts":1770834460,"event":"BotPosition","px":346.39,"py":585.88},{"ts":1770834465,"event":"BotPosition","px":357.83,"py":606.72},{"ts":1770834470,"event":"BotPosition","px":365.06,"py":617.02},{"ts":1770834475,"event":"BotPosition","px":359.58,"py":598.41},{"ts":1770834480,"event":"BotPosition","px":357.82,"py":580.81},{"ts":1770834485,"event":"BotPosition","px":356.07,"py":592.46},{"ts":1770834490,"event":"BotPosition","px":349.0,"py":604.74},{"ts":1770834495,"event":"BotPosition","px":337.51,"py":615.02},{"ts":1770834500,"event":"BotPosition","px":314.99,"py":607.47},{"ts":1770834505,"event":"BotPosition","px":301.97,"py":598.02},{"ts":1770834510,"event":"BotPosition","px":284.76,"py":588.39},{"ts":1770834515,"event":"BotPosition","px":269.22,"py":569.53},{"ts":1770834520,"event":"BotPosition","px":259.86,"py":549.16},{"ts":1770834525,"event":"BotPosition","px":239.15,"py":540.54},{"ts":1770834530,"event":"BotPosition","px":217.88,"py":527.05},{"ts":1770834534,"event":"BotKill","px":204.35,"py":520.12},{"ts":1770834535,"event":"BotPosition","px":208.6,"py":520.93},{"ts":1770834540,"event":"BotPosition","px":229.54,"py":534.58},{"ts":1770834546,"event":"BotPosition","px":249.12,"py":549.47},{"ts":1770834551,"event":"BotPosition","px":265.24,"py":568.62},{"ts":1770834556,"event":"BotPosition","px":278.59,"py":579.98},{"ts":1770834561,"event":"BotPosition","px":300.49,"py":591.65},{"ts":1770834566,"event":"BotPosition","px":324.59,"py":597.89},{"ts":1770834571,"event":"BotPosition","px":349.77,"py":599.8},{"ts":1770834576,"event":"BotPosition","px":364.04,"py":601.34},{"ts":1770834580,"event":"BotKilled","px":365.1,"py":599.56}]},"1432":{"is_bot":true,"events":[{"ts":1770834354,"event":"BotPosition","px":171.93,"py":377.36},{"ts":1770834359,"event":"BotPosition","px":187.04,"py":381.17},{"ts":1770834364,"event":"BotPosition","px":196.33,"py":385.34},{"ts":1770834370,"event":"BotPosition","px":193.07,"py":399.45},{"ts":1770834375,"event":"BotPosition","px":204.34,"py":406.12},{"ts":1770834385,"event":"BotPosition","px":204.76,"py":425.86},{"ts":1770834390,"event":"BotPosition","px":216.3,"py":441.44},{"ts":1770834395,"event":"BotPosition","px":236.59,"py":446.1},{"ts":1770834400,"event":"BotPosition","px":226.02,"py":458.6},{"ts":1770834405,"event":"BotPosition","px":231.83,"py":475.28},{"ts":1770834410,"event":"BotPosition","px":234.05,"py":493.91},{"ts":1770834415,"event":"BotPosition","px":234.71,"py":514.23},{"ts":1770834420,"event":"BotPosition","px":239.27,"py":535.07},{"ts":1770834425,"event":"BotPosition","px":251.5,"py":548.92},{"ts":1770834430,"event":"BotPosition","px":272.26,"py":557.83},{"ts":1770834435,"event":"BotPosition","px":289.48,"py":553.59},{"ts":1770834438,"event":"BotKill","px":296.92,"py":553.33},{"ts":1770834440,"event":"BotPosition","px":301.52,"py":550.59},{"ts":1770834445,"event":"BotPosition","px":309.81,"py":534.21},{"ts":1770834450,"event":"BotPosition","px":319.3,"py":543.53},{"ts":1770834455,"event":"BotPosition","px":338.43,"py":554.96},{"ts":1770834460,"event":"BotPosition","px":355.2,"py":569.29},{"ts":1770834465,"event":"BotPosition","px":338.63,"py":569.59},{"ts":1770834470,"event":"BotPosition","px":346.74,"py":572.82},{"ts":1770834475,"event":"BotPosition","px":359.79,"py":583.98},{"ts":1770834480,"event":"BotPosition","px":353.29,"py":586.08},{"ts":1770834485,"event":"BotPosition","px":341.66,"py":591.42},{"ts":1770834490,"event":"BotPosition","px":329.98,"py":592.3},{"ts":1770834495,"event":"BotPosition","px":323.35,"py":598.27},{"ts":1770834500,"event":"BotPosition","px":318.93,"py":608.29},{"ts":1770834505,"event":"BotPosition","px":306.88,"py":602.03},{"ts":1770834510,"event":"BotPosition","px":301.38,"py":584.71},{"ts":1770834515,"event":"BotPosition","px":284.14,"py":581.14},{"ts":1770834520,"event":"BotPosition","px":267.49,"py":584.01},{"ts":1770834525,"event":"BotPosition","px":253.4,"py":563.65},{"ts":1770834530,"event":"BotPosition","px":244.39,"py":547.38},{"ts":1770834535,"event":"BotPosition","px":237.91,"py":546.42},{"ts":1770834540,"event":"BotPosition","px":236.35,"py":537.67},{"ts":1770834546,"event":"BotPosition","px":228.9,"py":516.64},{"ts":1770834551,"event":"BotPosition","px":234.15,"py":522.12},{"ts":1770834556,"event":"BotPosition","px":244.72,"py":544.31},{"ts":1770834561,"event":"BotPosition","px":243.38,"py":564.67},{"ts":1770834566,"event":"BotPosition","px":232.0,"py":563.37},{"ts":1770834571,"event":"BotPosition","px":241.76,"py":566.92},{"ts":1770834576,"event":"BotPosition","px":260.4,"py":573.71},{"ts":1770834581,"event":"BotPosition","px":284.36,"py":579.94},{"ts":1770834586,"event":"BotPosition","px":301.02,"py":592.33},{"ts":1770834591,"event":"BotPosition","px":313.99,"py":597.24},{"ts":1770834596,"event":"BotPosition","px":336.26,"py":594.24},{"ts":1770834600,"event":"BotKilled","px":344.32,"py":592.46}]},"1435":{"is_bot":true,"events":[{"ts":1770834354,"event":"BotPosition","px":175.11,"py":377.31},{"ts":1770834359,"event":"BotPosition","px":188.79,"py":381.32},{"ts":1770834364,"event":"BotPosition","px":202.12,"py":387.63},{"ts":1770834370,"event":"BotPosition","px":206.97,"py":393.4},{"ts":1770834375,"event":"BotPosition","px":203.52,"py":416.37},{"ts":1770834380,"event":"BotPosition","px":220.54,"py":430.14},{"ts":1770834385,"event":"BotPosition","px":229.17,"py":440.44},{"ts":1770834390,"event":"BotPosition","px":227.27,"py":432.01},{"ts":1770834395,"event":"BotPosition","px":241.35,"py":446.36},{"ts":1770834400,"event":"BotPosition","px":231.6,"py":462.19},{"ts":1770834405,"event":"BotPosition","px":226.91,"py":480.68},{"ts":1770834410,"event":"BotPosition","px":227.54,"py":502.78},{"ts":1770834415,"event":"BotPosition","px":235.03,"py":524.92},{"ts":1770834420,"event":"BotPosition","px":247.43,"py":540.36},{"ts":1770834425,"event":"BotPosition","px":259.91,"py":552.42},{"ts":1770834430,"event":"BotPosition","px":270.99,"py":555.87},{"ts":1770834435,"event":"BotPosition","px":290.09,"py":555.33},{"ts":1770834440,"event":"BotPosition","px":301.7,"py":556.81},{"ts":1770834445,"event":"BotPosition","px":303.42,"py":554.44},{"ts":1770834450,"event":"BotPosition","px":322.17,"py":545.33},{"ts":1770834455,"event":"BotPosition","px":344.13,"py":547.99},{"ts":1770834460,"event":"BotPosition","px":360.33,"py":545.34},{"ts":1770834465,"event":"BotPosition","px":348.15,"py":557.14},{"ts":1770834470,"event":"BotPosition","px":348.55,"py":572.03},{"ts":1770834475,"event":"BotPosition","px":345.27,"py":575.84},{"ts":1770834480,"event":"BotPosition","px":364.16,"py":585.76},{"ts":1770834485,"event":"BotPosition","px":381.97,"py":596.65},{"ts":1770834490,"event":"BotPosition","px":365.78,"py":609.22},{"ts":1770834495,"event":"BotPosition","px":352.16,"py":610.32},{"ts":1770834500,"event":"BotPosition","px":354.2,"py":615.17},{"ts":1770834510,"event":"BotPosition","px":338.14,"py":615.31},{"ts":1770834515,"event":"BotPosition","px":336.69,"py":615.21},{"ts":1770834520,"event":"BotPosition","px":337.28,"py":611.76},{"ts":1770834524,"event":"BotKilled","px":334.69,"py":611.58}]},"1438":{"is_bot":true,"events":[{"ts":1770834354,"event":"BotPosition","px":809.2,"py":540.59},{"ts":1770834359,"event":"BotPosition","px":819.05,"py":524.48},{"ts":1770834364,"event":"BotPosition","px":825.54,"py":511.57},{"ts":1770834370,"event":"BotPosition","px":827.54,"py":489.08},{"ts":1770834375,"event":"BotPosition","px":837.12,"py":468.68},{"ts":1770834380,"event":"BotPosition","px":839.12,"py":452.75},{"ts":1770834385,"event":"BotPosition","px":852.51,"py":444.4},{"ts":1770834390,"event":"BotPosition","px":860.58,"py":441.55},{"ts":1770834395,"event":"BotPosition","px":849.37,"py":439.32},{"ts":1770834400,"event":"BotPosition","px":825.39,"py":433.15},{"ts":1770834405,"event":"BotPosition","px":800.76,"py":430.64},{"ts":1770834410,"event":"BotPosition","px":784.06,"py":444.56},{"ts":1770834415,"event":"BotPosition","px":787.12,"py":459.62},{"ts":1770834420,"event":"BotPosition","px":774.79,"py":474.37},{"ts":1770834425,"event":"BotPosition","px":771.9,"py":474.65},{"ts":1770834430,"event":"BotPosition","px":778.49,"py":456.79},{"ts":1770834435,"event":"BotPosition","px":788.85,"py":434.34},{"ts":1770834440,"event":"BotPosition","px":812.52,"py":431.93},{"ts":1770834445,"event":"BotPosition","px":837.42,"py":434.43},{"ts":1770834450,"event":"BotPosition","px":853.67,"py":446.56},{"ts":1770834455,"event":"BotPosition","px":828.85,"py":444.34},{"ts":1770834460,"event":"BotPosition","px":823.38,"py":454.52},{"ts":1770834465,"event":"BotPosition","px":805.56,"py":436.79},{"ts":1770834470,"event":"BotPosition","px":796.67,"py":440.76},{"ts":1770834475,"event":"BotPosition","px":809.97,"py":462.23},{"ts":1770834480,"event":"BotPosition","px":795.53,"py":454.07},{"ts":1770834485,"event":"BotPosition","px":788.66,"py":455.48},{"ts":1770834490,"event":"BotPosition","px":785.48,"py":467.71},{"ts":1770834495,"event":"BotPosition","px":790.98,"py":487.67},{"ts":1770834500,"event":"BotPosition","px":782.39,"py":480.6},{"ts":1770834505,"event":"BotPosition","px":766.27,"py":471.28},{"ts":1770834510,"event":"BotPosition","px":766.15,"py":483.36},{"ts":1770834515,"event":"BotPosition","px":752.46,"py":490.83},{"ts":1770834520,"event":"BotPosition","px":738.17,"py":501.15},{"ts":1770834525,"event":"BotPosition","px":762.41,"py":502.95},{"ts":1770834530,"event":"BotPosition","px":787.25,"py":500.73},{"ts":1770834535,"event":"BotPosition","px":786.86,"py":513.68},{"ts":1770834540,"event":"BotPosition","px":768.13,"py":528.52},{"ts":1770834546,"event":"BotPosition","px":743.14,"py":529.57},{"ts":1770834551,"event":"BotPosition","px":722.05,"py":518.74},{"ts":1770834556,"event":"BotPosition","px":717.79,"py":517.6},{"ts":1770834561,"event":"BotPosition","px":703.66,"py":528.25},{"ts":1770834566,"event":"BotPosition","px":704.02,"py":540.36},{"ts":1770834571,"event":"BotPosition","px":701.84,"py":562.75},{"ts":1770834576,"event":"BotPosition","px":681.1,"py":576.24},{"ts":1770834581,"event":"BotPosition","px":658.61,"py":580.06},{"ts":1770834586,"event":"BotPosition","px":659.3,"py":596.34},{"ts":1770834591,"event":"BotPosition","px":640.61,"py":595.14},{"ts":1770834596,"event":"BotPosition","px":616.33,"py":601.63},{"ts":1770834601,"event":"BotPosition","px":592.28,"py":608.98},{"ts":1770834606,"event":"BotPosition","px":567.14,"py":608.05},{"ts":1770834611,"event":"BotPosition","px":543.87,"py":603.96},{"ts":1770834616,"event":"BotPosition","px":541.26,"py":601.43},{"ts":1770834621,"event":"BotPosition","px":537.77,"py":585.8},{"ts":1770834626,"event":"BotPosition","px":526.56,"py":599.19},{"ts":1770834631,"event":"BotPosition","px":509.44,"py":604.28},{"ts":1770834636,"event":"BotPosition","px":512.69,"py":605.13},{"ts":1770834641,"event":"BotPosition","px":500.68,"py":612.06},{"ts":1770834646,"event":"BotPosition","px":494.33,"py":599.02},{"ts":1770834651,"event":"BotPosition","px":495.66,"py":599.17},{"ts":1770834656,"event":"BotPosition","px":500.45,"py":616.91},{"ts":1770834658,"event":"BotKill","px":497.24,"py":620.52},{"ts":1770834661,"event":"BotPosition","px":494.56,"py":627.3},{"ts":1770834666,"event":"BotPosition","px":491.67,"py":620.44},{"ts":1770834671,"event":"BotPosition","px":486.15,"py":636.29},{"ts":1770834676,"event":"BotPosition","px":478.19,"py":639.01},{"ts":1770834686,"event":"BotPosition","px":483.06,"py":635.9},{"ts":1770834691,"event":"BotPosition","px":486.3,"py":633.32},{"ts":1770834696,"event":"BotPosition","px":488.09,"py":630.37},{"ts":1770834701,"event":"BotPosition","px":489.0,"py":629.63},{"ts":1770834706,"event":"BotPosition","px":491.29,"py":630.56},{"ts":1770834711,"event":"BotPosition","px":493.83,"py":628.17},{"ts":1770834716,"event":"BotPosition","px":495.9,"py":624.33},{"ts":1770834724,"event":"BotKilled","px":494.72,"py":625.18}]},"1442":{"is_bot":true,"events":[{"ts":1770834354,"event":"BotPosition","px":801.5,"py":568.75},{"ts":1770834359,"event":"BotPosition","px":807.37,"py":545.17},{"ts":1770834364,"event":"BotPosition","px":818.03,"py":538.23},{"ts":1770834370,"event":"BotPosition","px":823.62,"py":525.12},{"ts":1770834375,"event":"BotPosition","px":832.07,"py":504.44},{"ts":1770834380,"event":"BotPosition","px":837.07,"py":489.66},{"ts":1770834385,"event":"BotPosition","px":836.6,"py":468.44},{"ts":1770834390,"event":"BotPosition","px":832.51,"py":446.69},{"ts":1770834395,"event":"BotPosition","px":853.13,"py":446.55},{"ts":1770834400,"event":"BotPosition","px":845.38,"py":432.9},{"ts":1770834405,"event":"BotPosition","px":821.34,"py":438.19},{"ts":1770834410,"event":"BotPosition","px":803.31,"py":436.54},{"ts":1770834415,"event":"BotPosition","px":786.37,"py":437.84},{"ts":1770834420,"event":"BotPosition","px":791.48,"py":447.87},{"ts":1770834425,"event":"BotPosition","px":797.56,"py":466.17},{"ts":1770834430,"event":"BotPosition","px":776.57,"py":465.56},{"ts":1770834435,"event":"BotPosition","px":776.84,"py":453.5},{"ts":1770834440,"event":"BotPosition","px":782.97,"py":445.53},{"ts":1770834445,"event":"BotPosition","px":794.06,"py":431.21},{"ts":1770834450,"event":"BotPosition","px":814.22,"py":426.29},{"ts":1770834455,"event":"BotPosition","px":830.37,"py":441.21},{"ts":1770834460,"event":"BotPosition","px":843.13,"py":451.01},{"ts":1770834465,"event":"BotPosition","px":828.12,"py":457.09},{"ts":1770834470,"event":"BotPosition","px":810.9,"py":450.55},{"ts":1770834475,"event":"BotPosition","px":801.05,"py":432.44},{"ts":1770834480,"event":"BotPosition","px":796.69,"py":441.67},{"ts":1770834485,"event":"BotPosition","px":791.21,"py":456.6},{"ts":1770834490,"event":"BotPosition","px":784.03,"py":454.85},{"ts":1770834495,"event":"BotPosition","px":795.85,"py":454.01},{"ts":1770834500,"event":"BotPosition","px":797.48,"py":473.31},{"ts":1770834505,"event":"BotPosition","px":791.46,"py":478.89},{"ts":1770834510,"event":"BotPosition","px":771.09,"py":477.04},{"ts":1770834515,"event":"BotPosition","px":766.32,"py":465.55},{"ts":1770834520,"event":"BotPosition","px":776.14,"py":454.41},{"ts":1770834525,"event":"BotPosition","px":769.74,"py":439.08},{"ts":1770834530,"event":"BotPosition","px":748.18,"py":445.48},{"ts":1770834535,"event":"BotPosition","px":737.33,"py":449.66},{"ts":1770834540,"event":"BotPosition","px":742.68,"py":454.19},{"ts":1770834546,"event":"BotPosition","px":734.47,"py":444.36},{"ts":1770834551,"event":"BotPosition","px":732.82,"py":448.93},{"ts":1770834556,"event":"BotPosition","px":742.14,"py":472.23},{"ts":1770834561,"event":"BotPosition","px":749.02,"py":482.76},{"ts":1770834566,"event":"BotPosition","px":764.34,"py":485.87},{"ts":1770834571,"event":"BotPosition","px":784.65,"py":494.73},{"ts":1770834576,"event":"BotPosition","px":789.09,"py":510.83},{"ts":1770834581,"event":"BotPosition","px":771.52,"py":527.55},{"ts":1770834586,"event":"BotPosition","px":747.11,"py":533.13},{"ts":1770834591,"event":"BotPosition","px":722.35,"py":537.71},{"ts":1770834596,"event":"BotPosition","px":699.18,"py":537.34},{"ts":1770834601,"event":"BotPosition","px":698.86,"py":544.68},{"ts":1770834606,"event":"BotPosition","px":696.76,"py":566.85},{"ts":1770834611,"event":"BotPosition","px":674.92,"py":578.6},{"ts":1770834616,"event":"BotPosition","px":649.99,"py":580.12},{"ts":1770834621,"event":"BotPosition","px":631.74,"py":578.98},{"ts":1770834626,"event":"BotPosition","px":610.88,"py":579.27},{"ts":1770834631,"event":"BotPosition","px":585.7,"py":578.11},{"ts":1770834636,"event":"BotPosition","px":562.48,"py":576.35},{"ts":1770834641,"event":"BotPosition","px":547.21,"py":586.99},{"ts":1770834646,"event":"BotPosition","px":535.1,"py":583.93},{"ts":1770834651,"event":"BotPosition","px":526.11,"py":599.4},{"ts":1770834656,"event":"BotPosition","px":506.55,"py":593.68},{"ts":1770834661,"event":"BotPosition","px":510.52,"py":610.07},{"ts":1770834666,"event":"BotPosition","px":501.85,"py":627.21},{"ts":1770834671,"event":"BotPosition","px":496.43,"py":631.04},{"ts":1770834676,"event":"BotPosition","px":498.7,"py":627.93},{"ts":1770834681,"event":"BotPosition","px":490.42,"py":634.03},{"ts":1770834691,"event":"BotPosition","px":493.57,"py":625.57},{"ts":1770834696,"event":"BotPosition","px":487.44,"py":628.88},{"ts":1770834701,"event":"BotPosition","px":493.21,"py":626.4},{"ts":1770834706,"event":"BotPosition","px":493.39,"py":633.63},{"ts":1770834711,"event":"BotPosition","px":500.99,"py":610.49},{"ts":1770834716,"event":"BotPosition","px":500.31,"py":615.93},{"ts":1770834722,"event":"BotPosition","px":490.87,"py":629.33},{"ts":1770834727,"event":"BotPosition","px":485.3,"py":643.92},{"ts":1770834727,"event":"BotKilled","px":485.16,"py":644.13}]},"1445":{"is_bot":true,"events":[{"ts":1770834354,"event":"BotPosition","px":800.79,"py":571.8},{"ts":1770834359,"event":"BotPosition","px":808.7,"py":552.11},{"ts":1770834364,"event":"BotPosition","px":823.19,"py":536.61},{"ts":1770834370,"event":"BotPosition","px":822.6,"py":524.21},{"ts":1770834375,"event":"BotPosition","px":816.29,"py":510.12},{"ts":1770834380,"event":"BotPosition","px":809.18,"py":514.63},{"ts":1770834385,"event":"BotPosition","px":811.71,"py":489.99},{"ts":1770834390,"event":"BotPosition","px":801.28,"py":471.24},{"ts":1770834395,"event":"BotPosition","px":795.54,"py":458.36},{"ts":1770834400,"event":"BotPosition","px":787.01,"py":435.0},{"ts":1770834405,"event":"BotPosition","px":803.82,"py":429.28},{"ts":1770834410,"event":"BotPosition","px":791.97,"py":413.02},{"ts":1770834415,"event":"BotPosition","px":779.43,"py":434.82},{"ts":1770834420,"event":"BotPosition","px":777.48,"py":451.18},{"ts":1770834425,"event":"BotPosition","px":776.82,"py":469.53},{"ts":1770834430,"event":"BotPosition","px":785.73,"py":454.92},{"ts":1770834435,"event":"BotPosition","px":769.07,"py":448.55},{"ts":1770834440,"event":"BotPosition","px":783.44,"py":448.65},{"ts":1770834445,"event":"BotPosition","px":799.35,"py":448.28},{"ts":1770834450,"event":"BotPosition","px":793.45,"py":436.33},{"ts":1770834455,"event":"BotPosition","px":803.22,"py":421.63},{"ts":1770834460,"event":"BotPosition","px":817.13,"py":423.52},{"ts":1770834465,"event":"BotPosition","px":835.98,"py":434.7},{"ts":1770834470,"event":"BotPosition","px":824.0,"py":436.91},{"ts":1770834475,"event":"BotPosition","px":810.75,"py":441.64},{"ts":1770834480,"event":"BotPosition","px":793.48,"py":433.43},{"ts":1770834485,"event":"BotPosition","px":796.88,"py":451.29},{"ts":1770834490,"event":"BotPosition","px":784.72,"py":463.19},{"ts":1770834495,"event":"BotPosition","px":782.05,"py":462.95},{"ts":1770834500,"event":"BotPosition","px":775.45,"py":446.48},{"ts":1770834505,"event":"BotPosition","px":774.39,"py":435.52},{"ts":1770834510,"event":"BotPosition","px":776.43,"py":456.59},{"ts":1770834515,"event":"BotPosition","px":786.53,"py":467.2},{"ts":1770834520,"event":"BotPosition","px":773.77,"py":475.32},{"ts":1770834525,"event":"BotPosition","px":756.05,"py":489.24},{"ts":1770834530,"event":"BotPosition","px":741.93,"py":492.09},{"ts":1770834535,"event":"BotPosition","px":756.27,"py":507.1},{"ts":1770834540,"event":"BotPosition","px":776.91,"py":503.48},{"ts":1770834546,"event":"BotPosition","px":793.38,"py":505.15},{"ts":1770834551,"event":"BotPosition","px":784.97,"py":521.51},{"ts":1770834556,"event":"BotPosition","px":762.1,"py":530.67},{"ts":1770834561,"event":"BotPosition","px":745.07,"py":530.23},{"ts":1770834566,"event":"BotPosition","px":726.99,"py":523.13},{"ts":1770834571,"event":"BotPosition","px":724.18,"py":511.86},{"ts":1770834576,"event":"BotPosition","px":718.89,"py":531.29},{"ts":1770834581,"event":"BotPosition","px":711.46,"py":549.26},{"ts":1770834586,"event":"BotPosition","px":700.16,"py":564.54},{"ts":1770834591,"event":"BotPosition","px":678.77,"py":577.85},{"ts":1770834596,"event":"BotPosition","px":659.79,"py":581.29},{"ts":1770834601,"event":"BotPosition","px":656.97,"py":588.37},{"ts":1770834611,"event":"BotPosition","px":656.31,"py":583.11},{"ts":1770834616,"event":"BotPosition","px":658.86,"py":585.18},{"ts":1770834626,"event":"BotPosition","px":633.52,"py":584.16},{"ts":1770834631,"event":"BotPosition","px":611.88,"py":571.14},{"ts":1770834636,"event":"BotPosition","px":590.82,"py":558.46},{"ts":1770834641,"event":"BotPosition","px":596.64,"py":580.14},{"ts":1770834646,"event":"BotPosition","px":587.6,"py":591.91},{"ts":1770834651,"event":"BotPosition","px":570.91,"py":573.19},{"ts":1770834656,"event":"BotPosition","px":552.8,"py":588.59},{"ts":1770834661,"event":"BotPosition","px":538.9,"py":600.5},{"ts":1770834666,"event":"BotPosition","px":529.29,"py":586.23},{"ts":1770834671,"event":"BotPosition","px":521.01,"py":598.11},{"ts":1770834676,"event":"BotPosition","px":514.67,"py":616.03},{"ts":1770834681,"event":"BotPosition","px":506.08,"py":612.99},{"ts":1770834686,"event":"BotPosition","px":500.51,"py":619.55},{"ts":1770834691,"event":"BotPosition","px":506.17,"py":606.05},{"ts":1770834696,"event":"BotPosition","px":500.68,"py":615.49},{"ts":1770834701,"event":"BotPosition","px":494.2,"py":626.82},{"ts":1770834706,"event":"BotPosition","px":491.12,"py":635.22},{"ts":1770834711,"event":"BotPosition","px":492.96,"py":630.69},{"ts":1770834716,"event":"BotPosition","px":495.1,"py":626.98},{"ts":1770834727,"event":"BotKilled","px":493.47,"py":628.38}]},"1448":{"is_bot":true,"events":[{"ts":1770834354,"event":"BotPosition","px":270.84,"py":333.56},{"ts":1770834359,"event":"BotPosition","px":291.53,"py":338.55},{"ts":1770834364,"event":"BotPosition","px":309.74,"py":339.21},{"ts":1770834370,"event":"BotPosition","px":313.88,"py":357.57},{"ts":1770834375,"event":"BotPosition","px":306.42,"py":345.67},{"ts":1770834380,"event":"BotPosition","px":289.78,"py":349.66},{"ts":1770834385,"event":"BotPosition","px":291.22,"py":350.61},{"ts":1770834390,"event":"BotPosition","px":285.7,"py":339.79},{"ts":1770834395,"event":"BotPosition","px":301.25,"py":338.94},{"ts":1770834400,"event":"BotPosition","px":289.16,"py":341.89},{"ts":1770834405,"event":"BotPosition","px":295.46,"py":346.46},{"ts":1770834410,"event":"BotPosition","px":314.78,"py":343.62},{"ts":1770834415,"event":"BotPosition","px":323.71,"py":347.05},{"ts":1770834420,"event":"BotPosition","px":336.44,"py":352.35},{"ts":1770834425,"event":"BotPosition","px":338.53,"py":349.64},{"ts":1770834430,"event":"BotPosition","px":328.64,"py":363.8},{"ts":1770834435,"event":"BotPosition","px":336.64,"py":382.25},{"ts":1770834440,"event":"BotPosition","px":350.36,"py":403.16},{"ts":1770834445,"event":"BotPosition","px":363.76,"py":423.28},{"ts":1770834450,"event":"BotPosition","px":360.07,"py":418.39},{"ts":1770834455,"event":"BotPosition","px":362.04,"py":393.59},{"ts":1770834460,"event":"BotPosition","px":367.8,"py":368.99},{"ts":1770834465,"event":"BotPosition","px":376.9,"py":347.76},{"ts":1770834470,"event":"BotPosition","px":389.68,"py":342.38},{"ts":1770834475,"event":"BotPosition","px":411.27,"py":333.6},{"ts":1770834480,"event":"BotPosition","px":436.03,"py":338.27},{"ts":1770834485,"event":"BotPosition","px":458.47,"py":332.23},{"ts":1770834490,"event":"BotPosition","px":479.19,"py":318.6},{"ts":1770834495,"event":"BotPosition","px":494.19,"py":309.24},{"ts":1770834500,"event":"BotPosition","px":513.5,"py":319.74},{"ts":1770834505,"event":"BotPosition","px":522.63,"py":322.11},{"ts":1770834510,"event":"BotPosition","px":520.26,"py":306.74},{"ts":1770834515,"event":"BotPosition","px":526.84,"py":285.58},{"ts":1770834520,"event":"BotPosition","px":528.15,"py":282.82},{"ts":1770834525,"event":"BotPosition","px":528.99,"py":281.19},{"ts":1770834530,"event":"BotPosition","px":523.86,"py":290.74},{"ts":1770834535,"event":"BotPosition","px":522.01,"py":294.27},{"ts":1770834540,"event":"BotPosition","px":520.65,"py":297.68},{"ts":1770834546,"event":"BotPosition","px":519.43,"py":302.31},{"ts":1770834551,"event":"BotPosition","px":518.4,"py":311.26},{"ts":1770834556,"event":"BotPosition","px":516.3,"py":315.9},{"ts":1770834561,"event":"BotPosition","px":514.02,"py":319.73},{"ts":1770834566,"event":"BotPosition","px":500.57,"py":320.97},{"ts":1770834576,"event":"BotPosition","px":495.53,"py":321.24},{"ts":1770834591,"event":"BotPosition","px":488.51,"py":321.62},{"ts":1770834601,"event":"BotPosition","px":472.01,"py":329.66},{"ts":1770834606,"event":"BotPosition","px":451.0,"py":342.64},{"ts":1770834611,"event":"BotPosition","px":444.73,"py":366.54},{"ts":1770834616,"event":"BotPosition","px":440.13,"py":390.33},{"ts":1770834621,"event":"BotPosition","px":423.85,"py":405.69},{"ts":1770834626,"event":"BotPosition","px":407.52,"py":419.05},{"ts":1770834631,"event":"BotPosition","px":383.17,"py":422.59},{"ts":1770834636,"event":"BotPosition","px":366.46,"py":424.8},{"ts":1770834641,"event":"BotPosition","px":391.25,"py":426.11},{"ts":1770834646,"event":"BotPosition","px":416.38,"py":427.43},{"ts":1770834651,"event":"BotPosition","px":438.74,"py":436.77},{"ts":1770834656,"event":"BotPosition","px":447.31,"py":451.13},{"ts":1770834661,"event":"BotPosition","px":444.64,"py":448.08},{"ts":1770834666,"event":"BotPosition","px":443.25,"py":444.04},{"ts":1770834671,"event":"BotPosition","px":443.01,"py":440.16},{"ts":1770834676,"event":"BotPosition","px":444.89,"py":436.24},{"ts":1770834681,"event":"BotPosition","px":444.33,"py":433.47},{"ts":1770834696,"event":"BotPosition","px":446.37,"py":432.45},{"ts":1770834701,"event":"BotPosition","px":459.46,"py":432.1},{"ts":1770834706,"event":"BotPosition","px":484.37,"py":434.36},{"ts":1770834711,"event":"BotPosition","px":500.82,"py":453.03},{"ts":1770834716,"event":"BotPosition","px":521.4,"py":460.17},{"ts":1770834722,"event":"BotPosition","px":534.82,"py":457.69},{"ts":1770834727,"event":"BotPosition","px":557.48,"py":446.9},{"ts":1770834732,"event":"BotPosition","px":566.36,"py":445.49},{"ts":1770834737,"event":"BotPosition","px":563.02,"py":443.55},{"ts":1770834747,"event":"BotPosition","px":564.35,"py":443.95},{"ts":1770834752,"event":"BotPosition","px":567.23,"py":446.27},{"ts":1770834757,"event":"BotPosition","px":565.54,"py":445.39},{"ts":1770834767,"event":"BotPosition","px":566.97,"py":446.58},{"ts":1770834772,"event":"BotPosition","px":586.23,"py":462.46},{"ts":1770834777,"event":"BotPosition","px":595.13,"py":449.25},{"ts":1770834782,"event":"BotPosition","px":603.34,"py":443.78},{"ts":1770834787,"event":"BotPosition","px":607.77,"py":463.84},{"ts":1770834792,"event":"BotPosition","px":617.38,"py":480.12},{"ts":1770834797,"event":"BotPosition","px":618.89,"py":483.73},{"ts":1770834802,"event":"BotPosition","px":620.71,"py":487.34},{"ts":1770834817,"event":"BotPosition","px":618.35,"py":485.18},{"ts":1770834822,"event":"BotPosition","px":615.84,"py":481.63},{"ts":1770834828,"event":"BotKilled","px":616.3,"py":482.41}]},"1452":{"is_bot":true,"events":[{"ts":1770834354,"event":"BotPosition","px":270.72,"py":337.53},{"ts":1770834359,"event":"BotPosition","px":270.36,"py":360.43},{"ts":1770834364,"event":"BotPosition","px":280.58,"py":343.82},{"ts":1770834370,"event":"BotPosition","px":301.66,"py":341.17},{"ts":1770834375,"event":"BotPosition","px":296.53,"py":332.96},{"ts":1770834380,"event":"BotPosition","px":285.0,"py":331.75},{"ts":1770834385,"event":"BotPosition","px":287.46,"py":350.18},{"ts":1770834390,"event":"BotPosition","px":271.21,"py":369.09},{"ts":1770834395,"event":"BotPosition","px":274.77,"py":347.44},{"ts":1770834400,"event":"BotPosition","px":290.31,"py":330.8},{"ts":1770834405,"event":"BotPosition","px":304.83,"py":335.55},{"ts":1770834410,"event":"BotPosition","px":289.61,"py":330.99},{"ts":1770834415,"event":"BotPosition","px":304.46,"py":336.7},{"ts":1770834420,"event":"BotPosition","px":317.19,"py":330.11},{"ts":1770834425,"event":"BotPosition","px":328.91,"py":331.48},{"ts":1770834430,"event":"BotPosition","px":347.49,"py":333.67},{"ts":1770834435,"event":"BotPosition","px":360.01,"py":343.94},{"ts":1770834440,"event":"BotPosition","px":365.02,"py":361.25},{"ts":1770834445,"event":"BotPosition","px":360.41,"py":385.46},{"ts":1770834450,"event":"BotPosition","px":346.59,"py":395.8},{"ts":1770834455,"event":"BotPosition","px":334.05,"py":408.84},{"ts":1770834460,"event":"BotPosition","px":352.23,"py":394.68},{"ts":1770834465,"event":"BotPosition","px":373.25,"py":385.99},{"ts":1770834470,"event":"BotPosition","px":370.4,"py":371.91},{"ts":1770834475,"event":"BotPosition","px":372.44,"py":350.47},{"ts":1770834480,"event":"BotPosition","px":382.88,"py":348.99},{"ts":1770834485,"event":"BotPosition","px":401.05,"py":333.45},{"ts":1770834490,"event":"BotPosition","px":423.22,"py":331.21},{"ts":1770834495,"event":"BotPosition","px":444.86,"py":340.36},{"ts":1770834500,"event":"BotPosition","px":458.22,"py":327.02},{"ts":1770834505,"event":"BotPosition","px":477.03,"py":328.97},{"ts":1770834510,"event":"BotPosition","px":500.09,"py":332.93},{"ts":1770834515,"event":"BotPosition","px":509.84,"py":329.0},{"ts":1770834520,"event":"BotPosition","px":519.71,"py":308.28},{"ts":1770834525,"event":"BotPosition","px":521.53,"py":322.59},{"ts":1770834530,"event":"BotPosition","px":516.02,"py":320.97},{"ts":1770834535,"event":"BotPosition","px":509.43,"py":302.26},{"ts":1770834540,"event":"BotPosition","px":517.07,"py":309.72},{"ts":1770834546,"event":"BotPosition","px":523.09,"py":292.0},{"ts":1770834547,"event":"BotKill","px":524.13,"py":290.32},{"ts":1770834551,"event":"BotPosition","px":520.46,"py":298.32},{"ts":1770834556,"event":"BotPosition","px":514.92,"py":318.76},{"ts":1770834561,"event":"BotPosition","px":519.47,"py":301.9},{"ts":1770834571,"event":"BotPosition","px":522.56,"py":316.91},{"ts":1770834576,"event":"BotPosition","px":517.3,"py":321.24},{"ts":1770834581,"event":"BotPosition","px":511.63,"py":302.05},{"ts":1770834586,"event":"BotPosition","px":513.24,"py":313.27},{"ts":1770834591,"event":"BotPosition","px":513.53,"py":325.87},{"ts":1770834596,"event":"BotPosition","px":515.64,"py":317.61},{"ts":1770834601,"event":"BotPosition","px":500.19,"py":324.42},{"ts":1770834606,"event":"BotPosition","px":484.12,"py":316.62},{"ts":1770834611,"event":"BotPosition","px":467.61,"py":328.79},{"ts":1770834616,"event":"BotPosition","px":452.39,"py":340.53},{"ts":1770834621,"event":"BotPosition","px":448.4,"py":350.25},{"ts":1770834626,"event":"BotPosition","px":445.57,"py":375.15},{"ts":1770834631,"event":"BotPosition","px":460.01,"py":385.48},{"ts":1770834636,"event":"BotPosition","px":440.27,"py":394.11},{"ts":1770834641,"event":"BotPosition","px":423.62,"py":407.65},{"ts":1770834646,"event":"BotPosition","px":412.81,"py":424.53},{"ts":1770834651,"event":"BotPosition","px":405.86,"py":426.94},{"ts":1770834656,"event":"BotPosition","px":425.84,"py":428.93},{"ts":1770834661,"event":"BotPosition","px":431.39,"py":427.94},{"ts":1770834666,"event":"BotPosition","px":423.76,"py":403.96},{"ts":1770834671,"event":"BotPosition","px":414.53,"py":390.56},{"ts":1770834676,"event":"BotPosition","px":425.42,"py":407.52},{"ts":1770834681,"event":"BotPosition","px":434.36,"py":430.92},{"ts":1770834686,"event":"BotPosition","px":443.8,"py":433.95},{"ts":1770834696,"event":"BotPosition","px":446.69,"py":431.46},{"ts":1770834701,"event":"BotPosition","px":453.45,"py":430.72},{"ts":1770834706,"event":"BotPosition","px":460.65,"py":429.95},{"ts":1770834711,"event":"BotPosition","px":465.79,"py":428.41},{"ts":1770834716,"event":"BotPosition","px":471.8,"py":432.8},{"ts":1770834722,"event":"BotPosition","px":479.53,"py":432.78},{"ts":1770834727,"event":"BotPosition","px":486.24,"py":432.76},{"ts":1770834732,"event":"BotPosition","px":493.24,"py":433.79},{"ts":1770834737,"event":"BotPosition","px":495.83,"py":440.85},{"ts":1770834742,"event":"BotPosition","px":498.9,"py":447.44},{"ts":1770834747,"event":"BotPosition","px":503.58,"py":451.99},{"ts":1770834752,"event":"BotPosition","px":511.19,"py":450.61},{"ts":1770834757,"event":"BotPosition","px":518.77,"py":449.76},{"ts":1770834762,"event":"BotPosition","px":526.47,"py":450.37},{"ts":1770834767,"event":"BotPosition","px":531.99,"py":444.51},{"ts":1770834772,"event":"BotPosition","px":539.73,"py":446.02},{"ts":1770834777,"event":"BotPosition","px":546.88,"py":447.44},{"ts":1770834782,"event":"BotPosition","px":554.46,"py":445.9},{"ts":1770834787,"event":"BotPosition","px":561.99,"py":444.37},{"ts":1770834792,"event":"BotPosition","px":568.95,"py":443.66},{"ts":1770834797,"event":"BotPosition","px":576.36,"py":443.23},{"ts":1770834802,"event":"BotPosition","px":584.07,"py":442.78},{"ts":1770834807,"event":"BotPosition","px":590.6,"py":442.6},{"ts":1770834812,"event":"BotPosition","px":595.97,"py":447.34},{"ts":1770834817,"event":"BotPosition","px":602.76,"py":443.73},{"ts":1770834822,"event":"BotPosition","px":609.44,"py":439.83},{"ts":1770834827,"event":"BotPosition","px":616.11,"py":435.94},{"ts":1770834832,"event":"BotPosition","px":608.22,"py":448.41},{"ts":1770834837,"event":"BotPosition","px":626.35,"py":449.88},{"ts":1770834842,"event":"BotPosition","px":623.59,"py":469.98},{"ts":1770834847,"event":"BotPosition","px":599.83,"py":471.26},{"ts":1770834852,"event":"BotPosition","px":612.16,"py":475.81},{"ts":1770834857,"event":"BotPosition","px":622.26,"py":493.99},{"ts":1770834862,"event":"BotPosition","px":632.8,"py":493.24},{"ts":1770834867,"event":"BotPosition","px":646.78,"py":493.7},{"ts":1770834872,"event":"BotPosition","px":636.25,"py":512.59},{"ts":1770834877,"event":"BotPosition","px":633.38,"py":515.58},{"ts":1770834882,"event":"BotPosition","px":646.83,"py":495.32},{"ts":1770834884,"event":"BotKilled","px":644.8,"py":490.24}]},"1455":{"is_bot":true,"events":[{"ts":1770834354,"event":"BotPosition","px":286.15,"py":328.56},{"ts":1770834359,"event":"BotPosition","px":303.04,"py":336.04},{"ts":1770834364,"event":"BotPosition","px":294.59,"py":342.37},{"ts":1770834375,"event":"BotPosition","px":313.78,"py":332.35},{"ts":1770834380,"event":"BotPosition","px":314.9,"py":336.88},{"ts":1770834385,"event":"BotPosition","px":299.5,"py":351.49},{"ts":1770834390,"event":"BotPosition","px":277.68,"py":342.56},{"ts":1770834395,"event":"BotPosition","px":297.63,"py":339.01},{"ts":1770834400,"event":"BotPosition","px":318.84,"py":332.75},{"ts":1770834405,"event":"BotPosition","px":303.36,"py":341.66},{"ts":1770834410,"event":"BotPosition","px":284.68,"py":350.2},{"ts":1770834415,"event":"BotPosition","px":295.27,"py":327.7},{"ts":1770834420,"event":"BotPosition","px":306.59,"py":338.03},{"ts":1770834425,"event":"BotPosition","px":321.92,"py":348.6},{"ts":1770834430,"event":"BotPosition","px":333.0,"py":338.47},{"ts":1770834435,"event":"BotPosition","px":354.52,"py":337.39},{"ts":1770834440,"event":"BotPosition","px":360.03,"py":357.17},{"ts":1770834445,"event":"BotPosition","px":363.77,"py":373.27},{"ts":1770834450,"event":"BotPosition","px":359.68,"py":398.11},{"ts":1770834455,"event":"BotPosition","px":344.81,"py":393.59},{"ts":1770834460,"event":"BotPosition","px":344.36,"py":386.1},{"ts":1770834465,"event":"BotPosition","px":361.19,"py":382.87},{"ts":1770834470,"event":"BotPosition","px":364.06,"py":369.76},{"ts":1770834475,"event":"BotPosition","px":365.93,"py":351.17},{"ts":1770834480,"event":"BotPosition","px":366.49,"py":347.16},{"ts":1770834485,"event":"BotPosition","px":390.38,"py":341.8},{"ts":1770834490,"event":"BotPosition","px":406.94,"py":332.99},{"ts":1770834495,"event":"BotPosition","px":431.98,"py":335.99},{"ts":1770834500,"event":"BotPosition","px":447.93,"py":338.44},{"ts":1770834505,"event":"BotPosition","px":462.63,"py":318.94},{"ts":1770834510,"event":"BotPosition","px":464.41,"py":294.12},{"ts":1770834515,"event":"BotPosition","px":480.64,"py":291.66},{"ts":1770834520,"event":"BotPosition","px":475.04,"py":286.99},{"ts":1770834525,"event":"BotPosition","px":473.52,"py":263.89},{"ts":1770834530,"event":"BotPosition","px":473.06,"py":243.2},{"ts":1770834535,"event":"BotPosition","px":482.8,"py":232.12},{"ts":1770834540,"event":"BotPosition","px":496.88,"py":250.76},{"ts":1770834546,"event":"BotPosition","px":502.33,"py":270.83},{"ts":1770834551,"event":"BotPosition","px":513.78,"py":291.32},{"ts":1770834556,"event":"BotPosition","px":510.89,"py":284.97},{"ts":1770834561,"event":"BotPosition","px":517.18,"py":300.31},{"ts":1770834566,"event":"BotPosition","px":516.12,"py":316.3},{"ts":1770834571,"event":"BotPosition","px":499.04,"py":309.75},{"ts":1770834576,"event":"BotPosition","px":488.2,"py":310.17},{"ts":1770834581,"event":"BotPosition","px":485.78,"py":333.19},{"ts":1770834586,"event":"BotPosition","px":499.03,"py":346.15},{"ts":1770834591,"event":"BotPosition","px":513.41,"py":327.48},{"ts":1770834596,"event":"BotPosition","px":506.58,"py":318.45},{"ts":1770834601,"event":"BotPosition","px":491.66,"py":309.01},{"ts":1770834606,"event":"BotPosition","px":488.58,"py":316.98},{"ts":1770834611,"event":"BotPosition","px":467.89,"py":330.48},{"ts":1770834616,"event":"BotPosition","px":453.3,"py":340.04},{"ts":1770834621,"event":"BotPosition","px":448.08,"py":351.52},{"ts":1770834626,"event":"BotPosition","px":444.86,"py":376.1},{"ts":1770834631,"event":"BotPosition","px":442.27,"py":395.88},{"ts":1770834636,"event":"BotPosition","px":431.78,"py":398.8},{"ts":1770834641,"event":"BotPosition","px":423.28,"py":417.17},{"ts":1770834651,"event":"BotPosition","px":424.17,"py":409.24},{"ts":1770834656,"event":"BotPosition","px":425.88,"py":424.92},{"ts":1770834661,"event":"BotPosition","px":442.04,"py":429.71},{"ts":1770834666,"event":"BotPosition","px":430.91,"py":414.58},{"ts":1770834671,"event":"BotPosition","px":432.35,"py":396.17},{"ts":1770834676,"event":"BotPosition","px":455.65,"py":388.77},{"ts":1770834681,"event":"BotPosition","px":441.58,"py":392.26},{"ts":1770834686,"event":"BotPosition","px":419.62,"py":398.74},{"ts":1770834691,"event":"BotPosition","px":414.53,"py":416.88},{"ts":1770834701,"event":"BotPosition","px":421.55,"py":402.88},{"ts":1770834706,"event":"BotPosition","px":412.47,"py":382.13},{"ts":1770834716,"event":"BotPosition","px":423.93,"py":401.71},{"ts":1770834722,"event":"BotPosition","px":432.2,"py":425.37},{"ts":1770834727,"event":"BotPosition","px":451.16,"py":439.76},{"ts":1770834732,"event":"BotPosition","px":466.48,"py":442.12},{"ts":1770834737,"event":"BotPosition","px":489.46,"py":431.94},{"ts":1770834742,"event":"BotPosition","px":512.51,"py":426.5},{"ts":1770834747,"event":"BotPosition","px":534.92,"py":424.66},{"ts":1770834752,"event":"BotPosition","px":554.95,"py":437.54},{"ts":1770834757,"event":"BotPosition","px":565.54,"py":444.37},{"ts":1770834772,"event":"BotPosition","px":559.11,"py":443.97},{"ts":1770834777,"event":"BotPosition","px":565.66,"py":445.92},{"ts":1770834782,"event":"BotPosition","px":567.19,"py":453.43},{"ts":1770834787,"event":"BotPosition","px":572.5,"py":451.39},{"ts":1770834792,"event":"BotPosition","px":579.19,"py":447.5},{"ts":1770834797,"event":"BotPosition","px":585.87,"py":443.62},{"ts":1770834802,"event":"BotPosition","px":589.62,"py":442.12},{"ts":1770834807,"event":"BotPosition","px":589.53,"py":449.8},{"ts":1770834811,"event":"BotKill","px":590.96,"py":453.94},{"ts":1770834812,"event":"BotPosition","px":590.58,"py":456.32},{"ts":1770834817,"event":"BotPosition","px":599.92,"py":470.46},{"ts":1770834822,"event":"BotPosition","px":611.15,"py":474.88},{"ts":1770834827,"event":"BotPosition","px":621.71,"py":492.76},{"ts":1770834847,"event":"BotPosition","px":619.69,"py":488.21},{"ts":1770834852,"event":"BotPosition","px":616.14,"py":483.01},{"ts":1770834857,"event":"BotPosition","px":616.68,"py":483.64},{"ts":1770834862,"event":"BotPosition","px":619.31,"py":486.88},{"ts":1770834867,"event":"BotPosition","px":622.6,"py":488.61},{"ts":1770834872,"event":"BotPosition","px":624.93,"py":492.31},{"ts":1770834875,"event":"BotKilled","px":625.71,"py":494.58}]},"fbf6abaf-0686-4f96-8cda-77071d195268":{"is_bot":false,"events":[{"ts":1770834349,"event":"Position","px":149.73,"py":645.23},{"ts":1770834359,"event":"Position","px":149.49,"py":644.12},{"ts":1770834364,"event":"Position","px":160.31,"py":628.56},{"ts":1770834370,"event":"Position","px":186.72,"py":616.42},{"ts":1770834375,"event":"Position","px":202.65,"py":616.76},{"ts":1770834380,"event":"Position","px":201.14,"py":627.23},{"ts":1770834381,"event":"Loot","px":201.14,"py":627.23},{"ts":1770834385,"event":"Position","px":202.7,"py":622.39},{"ts":1770834388,"event":"Loot","px":203.99,"py":618.76},{"ts":1770834390,"event":"Position","px":205.85,"py":620.51},{"ts":1770834395,"event":"Position","px":211.78,"py":624.33},{"ts":1770834397,"event":"Loot","px":211.78,"py":624.33},{"ts":1770834400,"event":"Position","px":213.52,"py":631.14},{"ts":1770834400,"event":"Loot","px":213.52,"py":631.14},{"ts":1770834400,"event":"Loot","px":213.52,"py":631.14},{"ts":1770834400,"event":"Loot","px":213.52,"py":631.14},{"ts":1770834405,"event":"Loot","px":207.89,"py":627.31},{"ts":1770834405,"event":"Position","px":207.89,"py":627.31},{"ts":1770834410,"event":"Position","px":213.4,"py":618.5},{"ts":1770834420,"event":"Position","px":221.12,"py":618.21},{"ts":1770834425,"event":"Position","px":215.35,"py":590.2},{"ts":1770834430,"event":"Position","px":213.8,"py":566.79},{"ts":1770834435,"event":"Position","px":218.55,"py":567.04},{"ts":1770834440,"event":"Position","px":231.3,"py":580.14},{"ts":1770834445,"event":"Position","px":241.93,"py":594.31},{"ts":1770834450,"event":"Position","px":268.92,"py":586.25},{"ts":1770834455,"event":"Position","px":284.53,"py":586.07},{"ts":1770834460,"event":"Position","px":307.6,"py":577.14},{"ts":1770834465,"event":"Position","px":317.97,"py":559.74},{"ts":1770834470,"event":"Position","px":327.39,"py":554.97},{"ts":1770834471,"event":"Loot","px":328.26,"py":553.03},{"ts":1770834471,"event":"Loot","px":328.26,"py":553.03},{"ts":1770834475,"event":"Position","px":338.19,"py":557.55},{"ts":1770834480,"event":"Position","px":339.11,"py":564.99},{"ts":1770834485,"event":"Position","px":337.14,"py":566.53},{"ts":1770834495,"event":"Position","px":337.2,"py":568.84},{"ts":1770834500,"event":"Position","px":342.34,"py":570.45},{"ts":1770834505,"event":"Position","px":355.04,"py":590.86},{"ts":1770834510,"event":"Position","px":348.95,"py":614.4},{"ts":1770834515,"event":"Position","px":346.84,"py":609.1},{"ts":1770834524,"event":"BotKill","px":341.08,"py":605.63},{"ts":1770834525,"event":"Position","px":339.89,"py":605.17},{"ts":1770834528,"event":"Loot","px":335.06,"py":610.85},{"ts":1770834528,"event":"Loot","px":335.06,"py":610.85},{"ts":1770834528,"event":"Loot","px":335.06,"py":610.85},{"ts":1770834530,"event":"Position","px":334.75,"py":608.36},{"ts":1770834535,"event":"Position","px":351.14,"py":608.41},{"ts":1770834540,"event":"Position","px":360.49,"py":617.66},{"ts":1770834546,"event":"Position","px":363.55,"py":622.96},{"ts":1770834551,"event":"Position","px":361.95,"py":630.71},{"ts":1770834554,"event":"Loot","px":361.2,"py":631.94},{"ts":1770834566,"event":"Position","px":354.96,"py":626.57},{"ts":1770834571,"event":"Position","px":351.13,"py":629.27},{"ts":1770834576,"event":"Position","px":359.17,"py":616.73},{"ts":1770834586,"event":"Position","px":368.44,"py":608.21},{"ts":1770834589,"event":"Loot","px":365.99,"py":599.87},{"ts":1770834591,"event":"Position","px":361.51,"py":596.23},{"ts":1770834596,"event":"Position","px":344.14,"py":587.55},{"ts":1770834600,"event":"BotKill","px":342.04,"py":594.18},{"ts":1770834601,"event":"Position","px":342.04,"py":594.18},{"ts":1770834603,"event":"Loot","px":344.34,"py":592.2},{"ts":1770834606,"event":"Position","px":346.43,"py":594.21},{"ts":1770834611,"event":"Position","px":366.16,"py":599.5},{"ts":1770834616,"event":"Loot","px":385.54,"py":603.22},{"ts":1770834616,"event":"Position","px":385.54,"py":603.22},{"ts":1770834621,"event":"Position","px":378.18,"py":601.21},{"ts":1770834626,"event":"Position","px":360.32,"py":585.57},{"ts":1770834630,"event":"Loot","px":353.51,"py":579.53},{"ts":1770834631,"event":"Position","px":349.13,"py":578.16},{"ts":1770834636,"event":"Position","px":338.54,"py":560.16},{"ts":1770834641,"event":"Position","px":350.01,"py":551.15},{"ts":1770834646,"event":"Position","px":353.77,"py":552.24},{"ts":1770834651,"event":"Position","px":382.59,"py":550.81},{"ts":1770834656,"event":"Position","px":412.31,"py":551.69},{"ts":1770834661,"event":"Position","px":439.39,"py":541.87},{"ts":1770834666,"event":"Position","px":458.73,"py":528.42},{"ts":1770834671,"event":"Position","px":474.47,"py":521.85},{"ts":1770834676,"event":"Position","px":483.21,"py":517.35},{"ts":1770834681,"event":"Position","px":499.66,"py":508.04},{"ts":1770834686,"event":"Position","px":527.14,"py":513.2},{"ts":1770834691,"event":"Position","px":552.68,"py":523.62},{"ts":1770834696,"event":"Position","px":577.52,"py":532.0},{"ts":1770834701,"event":"Position","px":605.19,"py":524.14},{"ts":1770834706,"event":"Position","px":623.7,"py":515.14},{"ts":1770834711,"event":"Position","px":644.92,"py":516.07},{"ts":1770834716,"event":"Position","px":668.19,"py":504.78},{"ts":1770834722,"event":"Position","px":671.94,"py":500.89},{"ts":1770834737,"event":"Position","px":668.7,"py":506.41},{"ts":1770834742,"event":"Position","px":659.82,"py":505.73},{"ts":1770834747,"event":"Position","px":649.96,"py":510.86},{"ts":1770834752,"event":"Position","px":645.02,"py":512.34},{"ts":1770834757,"event":"Position","px":637.09,"py":505.01},{"ts":1770834762,"event":"Position","px":634.42,"py":502.25},{"ts":1770834767,"event":"Position","px":628.2,"py":494.4},{"ts":1770834772,"event":"Position","px":623.83,"py":480.75},{"ts":1770834777,"event":"Position","px":618.72,"py":477.4},{"ts":1770834787,"event":"Position","px":614.13,"py":477.54},{"ts":1770834802,"event":"Position","px":606.95,"py":476.65},{"ts":1770834811,"event":"BotKilled","px":606.95,"py":476.65}]}}}